[
  {
    "Year": "2021",
    "County": "Adams",
    "Care_Type": "Center-based",
    "AgeGroup": "Infant",
    " Median Cost ": "NA",
    " 75th Percentile\nCost ": "NA",
    " State Subsidy\nRate ": "$897.00",
    "Median Cost\nas a % of Median Income": "NA",
    "": ""
  },
  {
    "Year": "2021",
    "County": "Adams",
    "Care_Type": "Center-based",
    "AgeGroup": "Toddler",
    " Median Cost ": "NA",
    " 75th Percentile\nCost ": "NA",
    " State Subsidy\nRate ": "$813.00",
    "Median Cost\nas a % of Median Income": "NA",
    "": ""
  },
  {
    "Year": "2021",
    "County": "Adams",
    "Care_Type": "Center-based",
    "AgeGroup": "Preschool",
    " Median Cost ": "NA",
    " 75th Percentile\nCost ": "NA",
    " State Subsidy\nRate ": "$741.00",
    "Median Cost\nas a % of Median Income": "NA",
    "": ""
  },
  {
    "Year": "2021",
    "County": "Adams",
    "Care_Type": "Center-based",
    "AgeGroup": "School Age",
    " Median Cost ": "NA",
    " 75th Percentile\nCost ": "NA",
    " State Subsidy\nRate ": "$731.00",
    "Median Cost\nas a % of Median Income": "NA",
    "": ""
  },
  {
    "Year": "2021",
    "County": "Adams",
    "Care_Type": "FCC",
    "AgeGroup": "Infant",
    " Median Cost ": "$975.00",
    " 75th Percentile\nCost ": "$1,083.00",
    " State Subsidy\nRate ": "$867.00",
    "Median Cost\nas a % of Median Income": "22.00%",
    "": ""
  },
  {
    "Year": "2021",
    "County": "Adams",
    "Care_Type": "FCC",
    "AgeGroup": "Toddler",
    " Median Cost ": "$867.00",
    " 75th Percentile\nCost ": "$1,062.00",
    " State Subsidy\nRate ": "$758.00",
    "Median Cost\nas a % of Median Income": "19.00%",
    "": ""
  },
  {
    "Year": "2021",
    "County": "Adams",
    "Care_Type": "FCC",
    "AgeGroup": "Preschool",
    " Median Cost ": "$802.00",
    " 75th Percentile\nCost ": "$948.00",
    " State Subsidy\nRate ": "$693.00",
    "Median Cost\nas a % of Median Income": "18.00%",
    "": ""
  },
  {
    "Year": "2021",
    "County": "Adams",
    "Care_Type": "FCC",
    "AgeGroup": "School Age",
    " Median Cost ": "$325.00",
    " 75th Percentile\nCost ": "$336.00",
    " State Subsidy\nRate ": "$650.00",
    "Median Cost\nas a % of Median Income": "7.00%",
    "": ""
  },
  {
    "Year": "2021",
    "County": "Asotin",
    "Care_Type": "Center-based",
    "AgeGroup": "Infant",
    " Median Cost ": "$793.00",
    " 75th Percentile\nCost ": "$849.00",
    " State Subsidy\nRate ": "$897.00",
    "Median Cost\nas a % of Median Income": "17.00%",
    "": ""
  },
  {
    "Year": "2021",
    "County": "Asotin",
    "Care_Type": "Center-based",
    "AgeGroup": "Toddler",
    " Median Cost ": "$749.00",
    " 75th Percentile\nCost ": "$796.00",
    " State Subsidy\nRate ": "$813.00",
    "Median Cost\nas a % of Median Income": "16.00%",
    "": ""
  },
  {
    "Year": "2021",
    "County": "Asotin",
    "Care_Type": "Center-based",
    "AgeGroup": "Preschool",
    " Median Cost ": "$695.00",
    " 75th Percentile\nCost ": "$754.00",
    " State Subsidy\nRate ": "$741.00",
    "Median Cost\nas a % of Median Income": "15.00%",
    "": ""
  },
  {
    "Year": "2021",
    "County": "Asotin",
    "Care_Type": "Center-based",
    "AgeGroup": "School Age",
    " Median Cost ": "$455.00",
    " 75th Percentile\nCost ": "$737.00",
    " State Subsidy\nRate ": "$731.00",
    "Median Cost\nas a % of Median Income": "10.00%",
    "": ""
  },
  {
    "Year": "2021",
    "County": "Asotin",
    "Care_Type": "FCC",
    "AgeGroup": "Infant",
    " Median Cost ": "NA",
    " 75th Percentile\nCost ": "NA",
    " State Subsidy\nRate ": "$867.00",
    "Median Cost\nas a % of Median Income": "NA",
    "": ""
  },
  {
    "Year": "2021",
    "County": "Asotin",
    "Care_Type": "FCC",
    "AgeGroup": "Toddler",
    " Median Cost ": "NA",
    " 75th Percentile\nCost ": "NA",
    " State Subsidy\nRate ": "$758.00",
    "Median Cost\nas a % of Median Income": "NA",
    "": ""
  },
  {
    "Year": "2021",
    "County": "Asotin",
    "Care_Type": "FCC",
    "AgeGroup": "Preschool",
    " Median Cost ": "NA",
    " 75th Percentile\nCost ": "NA",
    " State Subsidy\nRate ": "$693.00",
    "Median Cost\nas a % of Median Income": "NA",
    "": ""
  },
  {
    "Year": "2021",
    "County": "Asotin",
    "Care_Type": "FCC",
    "AgeGroup": "School Age",
    " Median Cost ": "NA",
    " 75th Percentile\nCost ": "NA",
    " State Subsidy\nRate ": "$650.00",
    "Median Cost\nas a % of Median Income": "NA",
    "": ""
  },
  {
    "Year": "2021",
    "County": "Benton",
    "Care_Type": "Center-based",
    "AgeGroup": "Infant",
    " Median Cost ": "$1,221.00",
    " 75th Percentile\nCost ": "$1,325.00",
    " State Subsidy\nRate ": "$1,235.00",
    "Median Cost\nas a % of Median Income": "20.00%",
    "": ""
  },
  {
    "Year": "2021",
    "County": "Benton",
    "Care_Type": "Center-based",
    "AgeGroup": "Toddler",
    " Median Cost ": "$1,062.00",
    " 75th Percentile\nCost ": "$1,125.00",
    " State Subsidy\nRate ": "$1,105.00",
    "Median Cost\nas a % of Median Income": "18.00%",
    "": ""
  },
  {
    "Year": "2021",
    "County": "Benton",
    "Care_Type": "Center-based",
    "AgeGroup": "Preschool",
    " Median Cost ": "$889.00",
    " 75th Percentile\nCost ": "$999.00",
    " State Subsidy\nRate ": "$1,018.00",
    "Median Cost\nas a % of Median Income": "15.00%",
    "": ""
  },
  {
    "Year": "2021",
    "County": "Benton",
    "Care_Type": "Center-based",
    "AgeGroup": "School Age",
    " Median Cost ": "$595.00",
    " 75th Percentile\nCost ": "$801.00",
    " State Subsidy\nRate ": "$778.00",
    "Median Cost\nas a % of Median Income": "10.00%",
    "": ""
  },
  {
    "Year": "2021",
    "County": "Benton",
    "Care_Type": "FCC",
    "AgeGroup": "Infant",
    " Median Cost ": "$880.00",
    " 75th Percentile\nCost ": "$1,083.00",
    " State Subsidy\nRate ": "$975.00",
    "Median Cost\nas a % of Median Income": "15.00%",
    "": ""
  },
  {
    "Year": "2021",
    "County": "Benton",
    "Care_Type": "FCC",
    "AgeGroup": "Toddler",
    " Median Cost ": "$775.00",
    " 75th Percentile\nCost ": "$975.00",
    " State Subsidy\nRate ": "$813.00",
    "Median Cost\nas a % of Median Income": "13.00%",
    "": ""
  },
  {
    "Year": "2021",
    "County": "Benton",
    "Care_Type": "FCC",
    "AgeGroup": "Preschool",
    " Median Cost ": "$737.00",
    " 75th Percentile\nCost ": "$842.00",
    " State Subsidy\nRate ": "$758.00",
    "Median Cost\nas a % of Median Income": "12.00%",
    "": ""
  },
  {
    "Year": "2021",
    "County": "Benton",
    "Care_Type": "FCC",
    "AgeGroup": "School Age",
    " Median Cost ": "$303.00",
    " 75th Percentile\nCost ": "$477.00",
    " State Subsidy\nRate ": "$693.00",
    "Median Cost\nas a % of Median Income": "5.00%",
    "": ""
  },
  {
    "Year": "2021",
    "County": "Chelan",
    "Care_Type": "Center-based",
    "AgeGroup": "Infant",
    " Median Cost ": "$975.00",
    " 75th Percentile\nCost ": "$1,148.00",
    " State Subsidy\nRate ": "$897.00",
    "Median Cost\nas a % of Median Income": "18.00%",
    "": ""
  },
  {
    "Year": "2021",
    "County": "Chelan",
    "Care_Type": "Center-based",
    "AgeGroup": "Toddler",
    " Median Cost ": "$825.00",
    " 75th Percentile\nCost ": "$888.00",
    " State Subsidy\nRate ": "$813.00",
    "Median Cost\nas a % of Median Income": "16.00%",
    "": ""
  },
  {
    "Year": "2021",
    "County": "Chelan",
    "Care_Type": "Center-based",
    "AgeGroup": "Preschool",
    " Median Cost ": "$808.00",
    " 75th Percentile\nCost ": "$863.00",
    " State Subsidy\nRate ": "$741.00",
    "Median Cost\nas a % of Median Income": "15.00%",
    "": ""
  },
  {
    "Year": "2021",
    "County": "Chelan",
    "Care_Type": "Center-based",
    "AgeGroup": "School Age",
    " Median Cost ": "$595.00",
    " 75th Percentile\nCost ": "$980.00",
    " State Subsidy\nRate ": "$731.00",
    "Median Cost\nas a % of Median Income": "11.00%",
    "": ""
  },
  {
    "Year": "2021",
    "County": "Chelan",
    "Care_Type": "FCC",
    "AgeGroup": "Infant",
    " Median Cost ": "$971.00",
    " 75th Percentile\nCost ": "$1,170.00",
    " State Subsidy\nRate ": "$867.00",
    "Median Cost\nas a % of Median Income": "18.00%",
    "": ""
  },
  {
    "Year": "2021",
    "County": "Chelan",
    "Care_Type": "FCC",
    "AgeGroup": "Toddler",
    " Median Cost ": "$841.00",
    " 75th Percentile\nCost ": "$1,083.00",
    " State Subsidy\nRate ": "$758.00",
    "Median Cost\nas a % of Median Income": "16.00%",
    "": ""
  },
  {
    "Year": "2021",
    "County": "Chelan",
    "Care_Type": "FCC",
    "AgeGroup": "Preschool",
    " Median Cost ": "$758.00",
    " 75th Percentile\nCost ": "$975.00",
    " State Subsidy\nRate ": "$693.00",
    "Median Cost\nas a % of Median Income": "14.00%",
    "": ""
  },
  {
    "Year": "2021",
    "County": "Chelan",
    "Care_Type": "FCC",
    "AgeGroup": "School Age",
    " Median Cost ": "$325.00",
    " 75th Percentile\nCost ": "$542.00",
    " State Subsidy\nRate ": "$650.00",
    "Median Cost\nas a % of Median Income": "6.00%",
    "": ""
  },
  {
    "Year": "2021",
    "County": "Clallam",
    "Care_Type": "Center-based",
    "AgeGroup": "Infant",
    " Median Cost ": "$1,268.00",
    " 75th Percentile\nCost ": "$1,316.00",
    " State Subsidy\nRate ": "$1,235.00",
    "Median Cost\nas a % of Median Income": "27.00%",
    "": ""
  },
  {
    "Year": "2021",
    "County": "Clallam",
    "Care_Type": "Center-based",
    "AgeGroup": "Toddler",
    " Median Cost ": "$1,127.00",
    " 75th Percentile\nCost ": "$1,131.00",
    " State Subsidy\nRate ": "$1,105.00",
    "Median Cost\nas a % of Median Income": "24.00%",
    "": ""
  },
  {
    "Year": "2021",
    "County": "Clallam",
    "Care_Type": "Center-based",
    "AgeGroup": "Preschool",
    " Median Cost ": "$1,018.00",
    " 75th Percentile\nCost ": "$1,045.00",
    " State Subsidy\nRate ": "$1,018.00",
    "Median Cost\nas a % of Median Income": "22.00%",
    "": ""
  },
  {
    "Year": "2021",
    "County": "Clallam",
    "Care_Type": "Center-based",
    "AgeGroup": "School Age",
    " Median Cost ": "$477.00",
    " 75th Percentile\nCost ": "$514.00",
    " State Subsidy\nRate ": "$778.00",
    "Median Cost\nas a % of Median Income": "10.00%",
    "": ""
  },
  {
    "Year": "2021",
    "County": "Clallam",
    "Care_Type": "FCC",
    "AgeGroup": "Infant",
    " Median Cost ": "$1,018.00",
    " 75th Percentile\nCost ": "$1,192.00",
    " State Subsidy\nRate ": "$975.00",
    "Median Cost\nas a % of Median Income": "22.00%",
    "": ""
  },
  {
    "Year": "2021",
    "County": "Clallam",
    "Care_Type": "FCC",
    "AgeGroup": "Toddler",
    " Median Cost ": "$883.00",
    " 75th Percentile\nCost ": "$994.00",
    " State Subsidy\nRate ": "$936.00",
    "Median Cost\nas a % of Median Income": "19.00%",
    "": ""
  },
  {
    "Year": "2021",
    "County": "Clallam",
    "Care_Type": "FCC",
    "AgeGroup": "Preschool",
    " Median Cost ": "$850.00",
    " 75th Percentile\nCost ": "$950.00",
    " State Subsidy\nRate ": "$823.00",
    "Median Cost\nas a % of Median Income": "18.00%",
    "": ""
  },
  {
    "Year": "2021",
    "County": "Clallam",
    "Care_Type": "FCC",
    "AgeGroup": "School Age",
    " Median Cost ": "$510.00",
    " 75th Percentile\nCost ": "$569.00",
    " State Subsidy\nRate ": "$704.00",
    "Median Cost\nas a % of Median Income": "11.00%",
    "": ""
  },
  {
    "Year": "2021",
    "County": "Clark",
    "Care_Type": "Center-based",
    "AgeGroup": "Infant",
    " Median Cost ": "$1,616.00",
    " 75th Percentile\nCost ": "$1,668.00",
    " State Subsidy\nRate ": "$1,654.00",
    "Median Cost\nas a % of Median Income": "25.00%",
    "": ""
  },
  {
    "Year": "2021",
    "County": "Clark",
    "Care_Type": "Center-based",
    "AgeGroup": "Toddler",
    " Median Cost ": "$1,369.00",
    " 75th Percentile\nCost ": "$1,495.00",
    " State Subsidy\nRate ": "$1,482.00",
    "Median Cost\nas a % of Median Income": "21.00%",
    "": ""
  },
  {
    "Year": "2021",
    "County": "Clark",
    "Care_Type": "Center-based",
    "AgeGroup": "Preschool",
    " Median Cost ": "$1,133.00",
    " 75th Percentile\nCost ": "$1,262.00",
    " State Subsidy\nRate ": "$1,249.00",
    "Median Cost\nas a % of Median Income": "17.00%",
    "": ""
  },
  {
    "Year": "2021",
    "County": "Clark",
    "Care_Type": "Center-based",
    "AgeGroup": "School Age",
    " Median Cost ": "$585.00",
    " 75th Percentile\nCost ": "$693.00",
    " State Subsidy\nRate ": "$946.00",
    "Median Cost\nas a % of Median Income": "9.00%",
    "": ""
  },
  {
    "Year": "2021",
    "County": "Clark",
    "Care_Type": "FCC",
    "AgeGroup": "Infant",
    " Median Cost ": "$867.00",
    " 75th Percentile\nCost ": "$1,083.00",
    " State Subsidy\nRate ": "$975.00",
    "Median Cost\nas a % of Median Income": "13.00%",
    "": ""
  },
  {
    "Year": "2021",
    "County": "Clark",
    "Care_Type": "FCC",
    "AgeGroup": "Toddler",
    " Median Cost ": "$812.00",
    " 75th Percentile\nCost ": "$975.00",
    " State Subsidy\nRate ": "$936.00",
    "Median Cost\nas a % of Median Income": "13.00%",
    "": ""
  },
  {
    "Year": "2021",
    "County": "Clark",
    "Care_Type": "FCC",
    "AgeGroup": "Preschool",
    " Median Cost ": "$764.00",
    " 75th Percentile\nCost ": "$877.00",
    " State Subsidy\nRate ": "$823.00",
    "Median Cost\nas a % of Median Income": "12.00%",
    "": ""
  },
  {
    "Year": "2021",
    "County": "Clark",
    "Care_Type": "FCC",
    "AgeGroup": "School Age",
    " Median Cost ": "$531.00",
    " 75th Percentile\nCost ": "$650.00",
    " State Subsidy\nRate ": "$704.00",
    "Median Cost\nas a % of Median Income": "8.00%",
    "": ""
  },
  {
    "Year": "2021",
    "County": "Columbia",
    "Care_Type": "Center-based",
    "AgeGroup": "Infant",
    " Median Cost ": "NA",
    " 75th Percentile\nCost ": "$0.00",
    " State Subsidy\nRate ": "$1,040.00",
    "Median Cost\nas a % of Median Income": "NA",
    "": ""
  },
  {
    "Year": "2021",
    "County": "Columbia",
    "Care_Type": "Center-based",
    "AgeGroup": "Toddler",
    " Median Cost ": "NA",
    " 75th Percentile\nCost ": "$0.00",
    " State Subsidy\nRate ": "$793.00",
    "Median Cost\nas a % of Median Income": "NA",
    "": ""
  },
  {
    "Year": "2021",
    "County": "Columbia",
    "Care_Type": "Center-based",
    "AgeGroup": "Preschool",
    " Median Cost ": "NA",
    " 75th Percentile\nCost ": "$0.00",
    " State Subsidy\nRate ": "$791.00",
    "Median Cost\nas a % of Median Income": "NA",
    "": ""
  },
  {
    "Year": "2021",
    "County": "Columbia",
    "Care_Type": "Center-based",
    "AgeGroup": "School Age",
    " Median Cost ": "NA",
    " 75th Percentile\nCost ": "$0.00",
    " State Subsidy\nRate ": "$593.00",
    "Median Cost\nas a % of Median Income": "NA",
    "": ""
  },
  {
    "Year": "2021",
    "County": "Columbia",
    "Care_Type": "FCC",
    "AgeGroup": "Infant",
    " Median Cost ": "NA",
    " 75th Percentile\nCost ": "$0.00",
    " State Subsidy\nRate ": "$975.00",
    "Median Cost\nas a % of Median Income": "NA",
    "": ""
  },
  {
    "Year": "2021",
    "County": "Columbia",
    "Care_Type": "FCC",
    "AgeGroup": "Toddler",
    " Median Cost ": "NA",
    " 75th Percentile\nCost ": "$0.00",
    " State Subsidy\nRate ": "$813.00",
    "Median Cost\nas a % of Median Income": "NA",
    "": ""
  },
  {
    "Year": "2021",
    "County": "Columbia",
    "Care_Type": "FCC",
    "AgeGroup": "Preschool",
    " Median Cost ": "NA",
    " 75th Percentile\nCost ": "$0.00",
    " State Subsidy\nRate ": "$758.00",
    "Median Cost\nas a % of Median Income": "NA",
    "": ""
  },
  {
    "Year": "2021",
    "County": "Columbia",
    "Care_Type": "FCC",
    "AgeGroup": "School Age",
    " Median Cost ": "NA",
    " 75th Percentile\nCost ": "$0.00",
    " State Subsidy\nRate ": "$693.00",
    "Median Cost\nas a % of Median Income": "NA",
    "": ""
  },
  {
    "Year": "2021",
    "County": "Cowlitz",
    "Care_Type": "Center-based",
    "AgeGroup": "Infant",
    " Median Cost ": "$1,160.00",
    " 75th Percentile\nCost ": "$1,235.00",
    " State Subsidy\nRate ": "$1,235.00",
    "Median Cost\nas a % of Median Income": "26.00%",
    "": ""
  },
  {
    "Year": "2021",
    "County": "Cowlitz",
    "Care_Type": "Center-based",
    "AgeGroup": "Toddler",
    " Median Cost ": "$1,050.00",
    " 75th Percentile\nCost ": "$1,105.00",
    " State Subsidy\nRate ": "$1,105.00",
    "Median Cost\nas a % of Median Income": "24.00%",
    "": ""
  },
  {
    "Year": "2021",
    "County": "Cowlitz",
    "Care_Type": "Center-based",
    "AgeGroup": "Preschool",
    " Median Cost ": "$960.00",
    " 75th Percentile\nCost ": "$1,018.00",
    " State Subsidy\nRate ": "$1,018.00",
    "Median Cost\nas a % of Median Income": "22.00%",
    "": ""
  },
  {
    "Year": "2021",
    "County": "Cowlitz",
    "Care_Type": "Center-based",
    "AgeGroup": "School Age",
    " Median Cost ": "$567.00",
    " 75th Percentile\nCost ": "$646.00",
    " State Subsidy\nRate ": "$778.00",
    "Median Cost\nas a % of Median Income": "13.00%",
    "": ""
  },
  {
    "Year": "2021",
    "County": "Cowlitz",
    "Care_Type": "FCC",
    "AgeGroup": "Infant",
    " Median Cost ": "$758.00",
    " 75th Percentile\nCost ": "$910.00",
    " State Subsidy\nRate ": "$975.00",
    "Median Cost\nas a % of Median Income": "17.00%",
    "": ""
  },
  {
    "Year": "2021",
    "County": "Cowlitz",
    "Care_Type": "FCC",
    "AgeGroup": "Toddler",
    " Median Cost ": "$758.00",
    " 75th Percentile\nCost ": "$846.00",
    " State Subsidy\nRate ": "$936.00",
    "Median Cost\nas a % of Median Income": "17.00%",
    "": ""
  },
  {
    "Year": "2021",
    "County": "Cowlitz",
    "Care_Type": "FCC",
    "AgeGroup": "Preschool",
    " Median Cost ": "$758.00",
    " 75th Percentile\nCost ": "$800.00",
    " State Subsidy\nRate ": "$823.00",
    "Median Cost\nas a % of Median Income": "17.00%",
    "": ""
  },
  {
    "Year": "2021",
    "County": "Cowlitz",
    "Care_Type": "FCC",
    "AgeGroup": "School Age",
    " Median Cost ": "$477.00",
    " 75th Percentile\nCost ": "$663.00",
    " State Subsidy\nRate ": "$704.00",
    "Median Cost\nas a % of Median Income": "11.00%",
    "": ""
  },
  {
    "Year": "2021",
    "County": "Douglas",
    "Care_Type": "Center-based",
    "AgeGroup": "Infant",
    " Median Cost ": "$458.00",
    " 75th Percentile\nCost ": "$679.00",
    " State Subsidy\nRate ": "$897.00",
    "Median Cost\nas a % of Median Income": "9.00%",
    "": ""
  },
  {
    "Year": "2021",
    "County": "Douglas",
    "Care_Type": "Center-based",
    "AgeGroup": "Toddler",
    " Median Cost ": "$800.00",
    " 75th Percentile\nCost ": "$813.00",
    " State Subsidy\nRate ": "$813.00",
    "Median Cost\nas a % of Median Income": "15.00%",
    "": ""
  },
  {
    "Year": "2021",
    "County": "Douglas",
    "Care_Type": "Center-based",
    "AgeGroup": "Preschool",
    " Median Cost ": "$735.00",
    " 75th Percentile\nCost ": "$780.00",
    " State Subsidy\nRate ": "$741.00",
    "Median Cost\nas a % of Median Income": "14.00%",
    "": ""
  },
  {
    "Year": "2021",
    "County": "Douglas",
    "Care_Type": "Center-based",
    "AgeGroup": "School Age",
    " Median Cost ": "NA",
    " 75th Percentile\nCost ": "$0.00",
    " State Subsidy\nRate ": "$731.00",
    "Median Cost\nas a % of Median Income": "NA",
    "": ""
  },
  {
    "Year": "2021",
    "County": "Douglas",
    "Care_Type": "FCC",
    "AgeGroup": "Infant",
    " Median Cost ": "$867.00",
    " 75th Percentile\nCost ": "$986.00",
    " State Subsidy\nRate ": "$867.00",
    "Median Cost\nas a % of Median Income": "16.00%",
    "": ""
  },
  {
    "Year": "2021",
    "County": "Douglas",
    "Care_Type": "FCC",
    "AgeGroup": "Toddler",
    " Median Cost ": "$758.00",
    " 75th Percentile\nCost ": "$868.00",
    " State Subsidy\nRate ": "$758.00",
    "Median Cost\nas a % of Median Income": "14.00%",
    "": ""
  },
  {
    "Year": "2021",
    "County": "Douglas",
    "Care_Type": "FCC",
    "AgeGroup": "Preschool",
    " Median Cost ": "$758.00",
    " 75th Percentile\nCost ": "$867.00",
    " State Subsidy\nRate ": "$693.00",
    "Median Cost\nas a % of Median Income": "14.00%",
    "": ""
  },
  {
    "Year": "2021",
    "County": "Douglas",
    "Care_Type": "FCC",
    "AgeGroup": "School Age",
    " Median Cost ": "$303.00",
    " 75th Percentile\nCost ": "$433.00",
    " State Subsidy\nRate ": "$650.00",
    "Median Cost\nas a % of Median Income": "6.00%",
    "": ""
  },
  {
    "Year": "2021",
    "County": "Ferry",
    "Care_Type": "Center-based",
    "AgeGroup": "Infant",
    " Median Cost ": "$765.00",
    " 75th Percentile\nCost ": "$765.00",
    " State Subsidy\nRate ": "$897.00",
    "Median Cost\nas a % of Median Income": "19.00%",
    "": ""
  },
  {
    "Year": "2021",
    "County": "Ferry",
    "Care_Type": "Center-based",
    "AgeGroup": "Toddler",
    " Median Cost ": "$703.00",
    " 75th Percentile\nCost ": "$703.00",
    " State Subsidy\nRate ": "$813.00",
    "Median Cost\nas a % of Median Income": "17.00%",
    "": ""
  },
  {
    "Year": "2021",
    "County": "Ferry",
    "Care_Type": "Center-based",
    "AgeGroup": "Preschool",
    " Median Cost ": "$544.00",
    " 75th Percentile\nCost ": "$544.00",
    " State Subsidy\nRate ": "$741.00",
    "Median Cost\nas a % of Median Income": "13.00%",
    "": ""
  },
  {
    "Year": "2021",
    "County": "Ferry",
    "Care_Type": "Center-based",
    "AgeGroup": "School Age",
    " Median Cost ": "NA",
    " 75th Percentile\nCost ": "NA",
    " State Subsidy\nRate ": "$731.00",
    "Median Cost\nas a % of Median Income": "NA",
    "": ""
  },
  {
    "Year": "2021",
    "County": "Ferry",
    "Care_Type": "FCC",
    "AgeGroup": "Infant",
    " Median Cost ": "$867.00",
    " 75th Percentile\nCost ": "$867.00",
    " State Subsidy\nRate ": "$867.00",
    "Median Cost\nas a % of Median Income": "21.00%",
    "": ""
  },
  {
    "Year": "2021",
    "County": "Ferry",
    "Care_Type": "FCC",
    "AgeGroup": "Toddler",
    " Median Cost ": "$758.00",
    " 75th Percentile\nCost ": "$758.00",
    " State Subsidy\nRate ": "$758.00",
    "Median Cost\nas a % of Median Income": "18.00%",
    "": ""
  },
  {
    "Year": "2021",
    "County": "Ferry",
    "Care_Type": "FCC",
    "AgeGroup": "Preschool",
    " Median Cost ": "$693.00",
    " 75th Percentile\nCost ": "$693.00",
    " State Subsidy\nRate ": "$693.00",
    "Median Cost\nas a % of Median Income": "17.00%",
    "": ""
  },
  {
    "Year": "2021",
    "County": "Ferry",
    "Care_Type": "FCC",
    "AgeGroup": "School Age",
    " Median Cost ": "$234.00",
    " 75th Percentile\nCost ": "$234.00",
    " State Subsidy\nRate ": "$650.00",
    "Median Cost\nas a % of Median Income": "6.00%",
    "": ""
  },
  {
    "Year": "2021",
    "County": "Franklin",
    "Care_Type": "Center-based",
    "AgeGroup": "Infant",
    " Median Cost ": "$1,048.00",
    " 75th Percentile\nCost ": "$1,077.00",
    " State Subsidy\nRate ": "$1,040.00",
    "Median Cost\nas a % of Median Income": "19.00%",
    "": ""
  },
  {
    "Year": "2021",
    "County": "Franklin",
    "Care_Type": "Center-based",
    "AgeGroup": "Toddler",
    " Median Cost ": "$1,050.00",
    " 75th Percentile\nCost ": "$1,240.00",
    " State Subsidy\nRate ": "$793.00",
    "Median Cost\nas a % of Median Income": "19.00%",
    "": ""
  },
  {
    "Year": "2021",
    "County": "Franklin",
    "Care_Type": "Center-based",
    "AgeGroup": "Preschool",
    " Median Cost ": "$850.00",
    " 75th Percentile\nCost ": "$977.00",
    " State Subsidy\nRate ": "$791.00",
    "Median Cost\nas a % of Median Income": "16.00%",
    "": ""
  },
  {
    "Year": "2021",
    "County": "Franklin",
    "Care_Type": "Center-based",
    "AgeGroup": "School Age",
    " Median Cost ": "$628.00",
    " 75th Percentile\nCost ": "$731.00",
    " State Subsidy\nRate ": "$593.00",
    "Median Cost\nas a % of Median Income": "11.00%",
    "": ""
  },
  {
    "Year": "2021",
    "County": "Franklin",
    "Care_Type": "FCC",
    "AgeGroup": "Infant",
    " Median Cost ": "$975.00",
    " 75th Percentile\nCost ": "$1,288.00",
    " State Subsidy\nRate ": "$975.00",
    "Median Cost\nas a % of Median Income": "18.00%",
    "": ""
  },
  {
    "Year": "2021",
    "County": "Franklin",
    "Care_Type": "FCC",
    "AgeGroup": "Toddler",
    " Median Cost ": "$867.00",
    " 75th Percentile\nCost ": "$1,083.00",
    " State Subsidy\nRate ": "$813.00",
    "Median Cost\nas a % of Median Income": "16.00%",
    "": ""
  },
  {
    "Year": "2021",
    "County": "Franklin",
    "Care_Type": "FCC",
    "AgeGroup": "Preschool",
    " Median Cost ": "$800.00",
    " 75th Percentile\nCost ": "$1,083.00",
    " State Subsidy\nRate ": "$758.00",
    "Median Cost\nas a % of Median Income": "15.00%",
    "": ""
  },
  {
    "Year": "2021",
    "County": "Franklin",
    "Care_Type": "FCC",
    "AgeGroup": "School Age",
    " Median Cost ": "$325.00",
    " 75th Percentile\nCost ": "$482.00",
    " State Subsidy\nRate ": "$693.00",
    "Median Cost\nas a % of Median Income": "6.00%",
    "": ""
  },
  {
    "Year": "2021",
    "County": "Garfield",
    "Care_Type": "Center-based",
    "AgeGroup": "Infant",
    " Median Cost ": "NA",
    " 75th Percentile\nCost ": "$0.00",
    " State Subsidy\nRate ": "$897.00",
    "Median Cost\nas a % of Median Income": "NA",
    "": ""
  },
  {
    "Year": "2021",
    "County": "Garfield",
    "Care_Type": "Center-based",
    "AgeGroup": "Toddler",
    " Median Cost ": "NA",
    " 75th Percentile\nCost ": "$0.00",
    " State Subsidy\nRate ": "$813.00",
    "Median Cost\nas a % of Median Income": "NA",
    "": ""
  },
  {
    "Year": "2021",
    "County": "Garfield",
    "Care_Type": "Center-based",
    "AgeGroup": "Preschool",
    " Median Cost ": "NA",
    " 75th Percentile\nCost ": "$0.00",
    " State Subsidy\nRate ": "$741.00",
    "Median Cost\nas a % of Median Income": "NA",
    "": ""
  },
  {
    "Year": "2021",
    "County": "Garfield",
    "Care_Type": "Center-based",
    "AgeGroup": "School Age",
    " Median Cost ": "NA",
    " 75th Percentile\nCost ": "$0.00",
    " State Subsidy\nRate ": "$731.00",
    "Median Cost\nas a % of Median Income": "NA",
    "": ""
  },
  {
    "Year": "2021",
    "County": "Garfield",
    "Care_Type": "FCC",
    "AgeGroup": "Infant",
    " Median Cost ": "NA",
    " 75th Percentile\nCost ": "$0.00",
    " State Subsidy\nRate ": "$867.00",
    "Median Cost\nas a % of Median Income": "NA",
    "": ""
  },
  {
    "Year": "2021",
    "County": "Garfield",
    "Care_Type": "FCC",
    "AgeGroup": "Toddler",
    " Median Cost ": "NA",
    " 75th Percentile\nCost ": "$0.00",
    " State Subsidy\nRate ": "$758.00",
    "Median Cost\nas a % of Median Income": "NA",
    "": ""
  },
  {
    "Year": "2021",
    "County": "Garfield",
    "Care_Type": "FCC",
    "AgeGroup": "Preschool",
    " Median Cost ": "NA",
    " 75th Percentile\nCost ": "$0.00",
    " State Subsidy\nRate ": "$693.00",
    "Median Cost\nas a % of Median Income": "NA",
    "": ""
  },
  {
    "Year": "2021",
    "County": "Garfield",
    "Care_Type": "FCC",
    "AgeGroup": "School Age",
    " Median Cost ": "NA",
    " 75th Percentile\nCost ": "$0.00",
    " State Subsidy\nRate ": "$650.00",
    "Median Cost\nas a % of Median Income": "NA",
    "": ""
  },
  {
    "Year": "2021",
    "County": "Grant",
    "Care_Type": "Center-based",
    "AgeGroup": "Infant",
    " Median Cost ": "$911.00",
    " 75th Percentile\nCost ": "$963.00",
    " State Subsidy\nRate ": "$897.00",
    "Median Cost\nas a % of Median Income": "18.00%",
    "": ""
  },
  {
    "Year": "2021",
    "County": "Grant",
    "Care_Type": "Center-based",
    "AgeGroup": "Toddler",
    " Median Cost ": "$848.00",
    " 75th Percentile\nCost ": "$875.00",
    " State Subsidy\nRate ": "$813.00",
    "Median Cost\nas a % of Median Income": "16.00%",
    "": ""
  },
  {
    "Year": "2021",
    "County": "Grant",
    "Care_Type": "Center-based",
    "AgeGroup": "Preschool",
    " Median Cost ": "$800.00",
    " 75th Percentile\nCost ": "$819.00",
    " State Subsidy\nRate ": "$741.00",
    "Median Cost\nas a % of Median Income": "16.00%",
    "": ""
  },
  {
    "Year": "2021",
    "County": "Grant",
    "Care_Type": "Center-based",
    "AgeGroup": "School Age",
    " Median Cost ": "$700.00",
    " 75th Percentile\nCost ": "$867.00",
    " State Subsidy\nRate ": "$731.00",
    "Median Cost\nas a % of Median Income": "14.00%",
    "": ""
  },
  {
    "Year": "2021",
    "County": "Grant",
    "Care_Type": "FCC",
    "AgeGroup": "Infant",
    " Median Cost ": "$867.00",
    " 75th Percentile\nCost ": "$1,001.00",
    " State Subsidy\nRate ": "$867.00",
    "Median Cost\nas a % of Median Income": "17.00%",
    "": ""
  },
  {
    "Year": "2021",
    "County": "Grant",
    "Care_Type": "FCC",
    "AgeGroup": "Toddler",
    " Median Cost ": "$758.00",
    " 75th Percentile\nCost ": "$918.00",
    " State Subsidy\nRate ": "$758.00",
    "Median Cost\nas a % of Median Income": "15.00%",
    "": ""
  },
  {
    "Year": "2021",
    "County": "Grant",
    "Care_Type": "FCC",
    "AgeGroup": "Preschool",
    " Median Cost ": "$714.00",
    " 75th Percentile\nCost ": "$867.00",
    " State Subsidy\nRate ": "$693.00",
    "Median Cost\nas a % of Median Income": "14.00%",
    "": ""
  },
  {
    "Year": "2021",
    "County": "Grant",
    "Care_Type": "FCC",
    "AgeGroup": "School Age",
    " Median Cost ": "$325.00",
    " 75th Percentile\nCost ": "$536.00",
    " State Subsidy\nRate ": "$650.00",
    "Median Cost\nas a % of Median Income": "6.00%",
    "": ""
  },
  {
    "Year": "2021",
    "County": "Grays Harbor",
    "Care_Type": "Center-based",
    "AgeGroup": "Infant",
    " Median Cost ": "$1,235.00",
    " 75th Percentile\nCost ": "$1,235.00",
    " State Subsidy\nRate ": "$1,235.00",
    "Median Cost\nas a % of Median Income": "27.00%",
    "": ""
  },
  {
    "Year": "2021",
    "County": "Grays Harbor",
    "Care_Type": "Center-based",
    "AgeGroup": "Toddler",
    " Median Cost ": "$1,105.00",
    " 75th Percentile\nCost ": "$1,105.00",
    " State Subsidy\nRate ": "$1,105.00",
    "Median Cost\nas a % of Median Income": "24.00%",
    "": ""
  },
  {
    "Year": "2021",
    "County": "Grays Harbor",
    "Care_Type": "Center-based",
    "AgeGroup": "Preschool",
    " Median Cost ": "$902.00",
    " 75th Percentile\nCost ": "$1,018.00",
    " State Subsidy\nRate ": "$1,018.00",
    "Median Cost\nas a % of Median Income": "20.00%",
    "": ""
  },
  {
    "Year": "2021",
    "County": "Grays Harbor",
    "Care_Type": "Center-based",
    "AgeGroup": "School Age",
    " Median Cost ": "$501.00",
    " 75th Percentile\nCost ": "$615.00",
    " State Subsidy\nRate ": "$778.00",
    "Median Cost\nas a % of Median Income": "11.00%",
    "": ""
  },
  {
    "Year": "2021",
    "County": "Grays Harbor",
    "Care_Type": "FCC",
    "AgeGroup": "Infant",
    " Median Cost ": "$945.00",
    " 75th Percentile\nCost ": "$975.00",
    " State Subsidy\nRate ": "$975.00",
    "Median Cost\nas a % of Median Income": "21.00%",
    "": ""
  },
  {
    "Year": "2021",
    "County": "Grays Harbor",
    "Care_Type": "FCC",
    "AgeGroup": "Toddler",
    " Median Cost ": "$850.00",
    " 75th Percentile\nCost ": "$936.00",
    " State Subsidy\nRate ": "$936.00",
    "Median Cost\nas a % of Median Income": "19.00%",
    "": ""
  },
  {
    "Year": "2021",
    "County": "Grays Harbor",
    "Care_Type": "FCC",
    "AgeGroup": "Preschool",
    " Median Cost ": "$798.00",
    " 75th Percentile\nCost ": "$823.00",
    " State Subsidy\nRate ": "$823.00",
    "Median Cost\nas a % of Median Income": "17.00%",
    "": ""
  },
  {
    "Year": "2021",
    "County": "Grays Harbor",
    "Care_Type": "FCC",
    "AgeGroup": "School Age",
    " Median Cost ": "$697.00",
    " 75th Percentile\nCost ": "$790.00",
    " State Subsidy\nRate ": "$704.00",
    "Median Cost\nas a % of Median Income": "15.00%",
    "": ""
  },
  {
    "Year": "2021",
    "County": "Island",
    "Care_Type": "Center-based",
    "AgeGroup": "Infant",
    " Median Cost ": "NA",
    " 75th Percentile\nCost ": "NA",
    " State Subsidy\nRate ": "$1,654.00",
    "Median Cost\nas a % of Median Income": "NA",
    "": ""
  },
  {
    "Year": "2021",
    "County": "Island",
    "Care_Type": "Center-based",
    "AgeGroup": "Toddler",
    " Median Cost ": "$938.00",
    " 75th Percentile\nCost ": "$1,036.00",
    " State Subsidy\nRate ": "$1,482.00",
    "Median Cost\nas a % of Median Income": "16.00%",
    "": ""
  },
  {
    "Year": "2021",
    "County": "Island",
    "Care_Type": "Center-based",
    "AgeGroup": "Preschool",
    " Median Cost ": "$840.00",
    " 75th Percentile\nCost ": "$1,120.00",
    " State Subsidy\nRate ": "$1,249.00",
    "Median Cost\nas a % of Median Income": "15.00%",
    "": ""
  },
  {
    "Year": "2021",
    "County": "Island",
    "Care_Type": "Center-based",
    "AgeGroup": "School Age",
    " Median Cost ": "$542.00",
    " 75th Percentile\nCost ": "$555.00",
    " State Subsidy\nRate ": "$946.00",
    "Median Cost\nas a % of Median Income": "9.00%",
    "": ""
  },
  {
    "Year": "2021",
    "County": "Island",
    "Care_Type": "FCC",
    "AgeGroup": "Infant",
    " Median Cost ": "$1,083.00",
    " 75th Percentile\nCost ": "$1,138.00",
    " State Subsidy\nRate ": "$1,192.00",
    "Median Cost\nas a % of Median Income": "19.00%",
    "": ""
  },
  {
    "Year": "2021",
    "County": "Island",
    "Care_Type": "FCC",
    "AgeGroup": "Toddler",
    " Median Cost ": "$845.00",
    " 75th Percentile\nCost ": "$1,083.00",
    " State Subsidy\nRate ": "$1,059.00",
    "Median Cost\nas a % of Median Income": "15.00%",
    "": ""
  },
  {
    "Year": "2021",
    "County": "Island",
    "Care_Type": "FCC",
    "AgeGroup": "Preschool",
    " Median Cost ": "$845.00",
    " 75th Percentile\nCost ": "$1,040.00",
    " State Subsidy\nRate ": "$1,040.00",
    "Median Cost\nas a % of Median Income": "15.00%",
    "": ""
  },
  {
    "Year": "2021",
    "County": "Island",
    "Care_Type": "FCC",
    "AgeGroup": "School Age",
    " Median Cost ": "$650.00",
    " 75th Percentile\nCost ": "$728.00",
    " State Subsidy\nRate ": "$867.00",
    "Median Cost\nas a % of Median Income": "11.00%",
    "": ""
  },
  {
    "Year": "2021",
    "County": "King",
    "Care_Type": "Center-based",
    "AgeGroup": "Infant",
    " Median Cost ": "$1,905.00",
    " 75th Percentile\nCost ": "$2,209.00",
    " State Subsidy\nRate ": "$2,074.00",
    "Median Cost\nas a % of Median Income": "23.00%",
    "": ""
  },
  {
    "Year": "2021",
    "County": "King",
    "Care_Type": "Center-based",
    "AgeGroup": "Toddler",
    " Median Cost ": "$1,677.00",
    " 75th Percentile\nCost ": "$1,958.00",
    " State Subsidy\nRate ": "$1,724.00",
    "Median Cost\nas a % of Median Income": "20.00%",
    "": ""
  },
  {
    "Year": "2021",
    "County": "King",
    "Care_Type": "Center-based",
    "AgeGroup": "Preschool",
    " Median Cost ": "$1,425.00",
    " 75th Percentile\nCost ": "$1,657.00",
    " State Subsidy\nRate ": "$1,556.00",
    "Median Cost\nas a % of Median Income": "17.00%",
    "": ""
  },
  {
    "Year": "2021",
    "County": "King",
    "Care_Type": "Center-based",
    "AgeGroup": "School Age",
    " Median Cost ": "$531.00",
    " 75th Percentile\nCost ": "$718.00",
    " State Subsidy\nRate ": "$975.00",
    "Median Cost\nas a % of Median Income": "6.00%",
    "": ""
  },
  {
    "Year": "2021",
    "County": "King",
    "Care_Type": "FCC",
    "AgeGroup": "Infant",
    " Median Cost ": "$1,300.00",
    " 75th Percentile\nCost ": "$1,500.00",
    " State Subsidy\nRate ": "$1,477.00",
    "Median Cost\nas a % of Median Income": "15.00%",
    "": ""
  },
  {
    "Year": "2021",
    "County": "King",
    "Care_Type": "FCC",
    "AgeGroup": "Toddler",
    " Median Cost ": "$1,200.00",
    " 75th Percentile\nCost ": "$1,408.00",
    " State Subsidy\nRate ": "$1,372.00",
    "Median Cost\nas a % of Median Income": "14.00%",
    "": ""
  },
  {
    "Year": "2021",
    "County": "King",
    "Care_Type": "FCC",
    "AgeGroup": "Preschool",
    " Median Cost ": "$1,062.00",
    " 75th Percentile\nCost ": "$1,300.00",
    " State Subsidy\nRate ": "$1,280.00",
    "Median Cost\nas a % of Median Income": "13.00%",
    "": ""
  },
  {
    "Year": "2021",
    "County": "King",
    "Care_Type": "FCC",
    "AgeGroup": "School Age",
    " Median Cost ": "$433.00",
    " 75th Percentile\nCost ": "$650.00",
    " State Subsidy\nRate ": "$867.00",
    "Median Cost\nas a % of Median Income": "5.00%",
    "": ""
  },
  {
    "Year": "2021",
    "County": "Kitsap",
    "Care_Type": "Center-based",
    "AgeGroup": "Infant",
    " Median Cost ": "$1,440.00",
    " 75th Percentile\nCost ": "$1,495.00",
    " State Subsidy\nRate ": "$1,355.00",
    "Median Cost\nas a % of Median Income": "22.00%",
    "": ""
  },
  {
    "Year": "2021",
    "County": "Kitsap",
    "Care_Type": "Center-based",
    "AgeGroup": "Toddler",
    " Median Cost ": "$1,192.00",
    " 75th Percentile\nCost ": "$1,326.00",
    " State Subsidy\nRate ": "$1,173.00",
    "Median Cost\nas a % of Median Income": "19.00%",
    "": ""
  },
  {
    "Year": "2021",
    "County": "Kitsap",
    "Care_Type": "Center-based",
    "AgeGroup": "Preschool",
    " Median Cost ": "$966.00",
    " 75th Percentile\nCost ": "$1,144.00",
    " State Subsidy\nRate ": "$1,042.00",
    "Median Cost\nas a % of Median Income": "15.00%",
    "": ""
  },
  {
    "Year": "2021",
    "County": "Kitsap",
    "Care_Type": "Center-based",
    "AgeGroup": "School Age",
    " Median Cost ": "$490.00",
    " 75th Percentile\nCost ": "$610.00",
    " State Subsidy\nRate ": "$758.00",
    "Median Cost\nas a % of Median Income": "8.00%",
    "": ""
  },
  {
    "Year": "2021",
    "County": "Kitsap",
    "Care_Type": "FCC",
    "AgeGroup": "Infant",
    " Median Cost ": "$1,036.00",
    " 75th Percentile\nCost ": "$1,083.00",
    " State Subsidy\nRate ": "$1,059.00",
    "Median Cost\nas a % of Median Income": "16.00%",
    "": ""
  },
  {
    "Year": "2021",
    "County": "Kitsap",
    "Care_Type": "FCC",
    "AgeGroup": "Toddler",
    " Median Cost ": "$867.00",
    " 75th Percentile\nCost ": "$1,034.00",
    " State Subsidy\nRate ": "$910.00",
    "Median Cost\nas a % of Median Income": "14.00%",
    "": ""
  },
  {
    "Year": "2021",
    "County": "Kitsap",
    "Care_Type": "FCC",
    "AgeGroup": "Preschool",
    " Median Cost ": "$812.00",
    " 75th Percentile\nCost ": "$995.00",
    " State Subsidy\nRate ": "$847.00",
    "Median Cost\nas a % of Median Income": "13.00%",
    "": ""
  },
  {
    "Year": "2021",
    "County": "Kitsap",
    "Care_Type": "FCC",
    "AgeGroup": "School Age",
    " Median Cost ": "$520.00",
    " 75th Percentile\nCost ": "$594.00",
    " State Subsidy\nRate ": "$774.00",
    "Median Cost\nas a % of Median Income": "8.00%",
    "": ""
  },
  {
    "Year": "2021",
    "County": "Kittitas",
    "Care_Type": "Center-based",
    "AgeGroup": "Infant",
    " Median Cost ": "$1,050.00",
    " 75th Percentile\nCost ": "$1,073.00",
    " State Subsidy\nRate ": "$1,040.00",
    "Median Cost\nas a % of Median Income": "22.00%",
    "": ""
  },
  {
    "Year": "2021",
    "County": "Kittitas",
    "Care_Type": "Center-based",
    "AgeGroup": "Toddler",
    " Median Cost ": "$921.00",
    " 75th Percentile\nCost ": "$960.00",
    " State Subsidy\nRate ": "$793.00",
    "Median Cost\nas a % of Median Income": "19.00%",
    "": ""
  },
  {
    "Year": "2021",
    "County": "Kittitas",
    "Care_Type": "Center-based",
    "AgeGroup": "Preschool",
    " Median Cost ": "$873.00",
    " 75th Percentile\nCost ": "$895.00",
    " State Subsidy\nRate ": "$791.00",
    "Median Cost\nas a % of Median Income": "18.00%",
    "": ""
  },
  {
    "Year": "2021",
    "County": "Kittitas",
    "Care_Type": "Center-based",
    "AgeGroup": "School Age",
    " Median Cost ": "$464.00",
    " 75th Percentile\nCost ": "$485.00",
    " State Subsidy\nRate ": "$593.00",
    "Median Cost\nas a % of Median Income": "10.00%",
    "": ""
  },
  {
    "Year": "2021",
    "County": "Kittitas",
    "Care_Type": "FCC",
    "AgeGroup": "Infant",
    " Median Cost ": "$910.00",
    " 75th Percentile\nCost ": "$1,083.00",
    " State Subsidy\nRate ": "$975.00",
    "Median Cost\nas a % of Median Income": "19.00%",
    "": ""
  },
  {
    "Year": "2021",
    "County": "Kittitas",
    "Care_Type": "FCC",
    "AgeGroup": "Toddler",
    " Median Cost ": "$802.00",
    " 75th Percentile\nCost ": "$939.00",
    " State Subsidy\nRate ": "$813.00",
    "Median Cost\nas a % of Median Income": "17.00%",
    "": ""
  },
  {
    "Year": "2021",
    "County": "Kittitas",
    "Care_Type": "FCC",
    "AgeGroup": "Preschool",
    " Median Cost ": "$802.00",
    " 75th Percentile\nCost ": "$865.00",
    " State Subsidy\nRate ": "$758.00",
    "Median Cost\nas a % of Median Income": "17.00%",
    "": ""
  },
  {
    "Year": "2021",
    "County": "Kittitas",
    "Care_Type": "FCC",
    "AgeGroup": "School Age",
    " Median Cost ": "$255.00",
    " 75th Percentile\nCost ": "$349.00",
    " State Subsidy\nRate ": "$693.00",
    "Median Cost\nas a % of Median Income": "5.00%",
    "": ""
  },
  {
    "Year": "2021",
    "County": "Klickitat",
    "Care_Type": "Center-based",
    "AgeGroup": "Infant",
    " Median Cost ": "No Rates Ava",
    " 75th Percentile\nCost ": "$0.00",
    " State Subsidy\nRate ": "$1,235.00",
    "Median Cost\nas a % of Median Income": "NA",
    "": ""
  },
  {
    "Year": "2021",
    "County": "Klickitat",
    "Care_Type": "Center-based",
    "AgeGroup": "Toddler",
    " Median Cost ": "$1,018.00",
    " 75th Percentile\nCost ": "$1,018.00",
    " State Subsidy\nRate ": "$1,105.00",
    "Median Cost\nas a % of Median Income": "20.00%",
    "": ""
  },
  {
    "Year": "2021",
    "County": "Klickitat",
    "Care_Type": "Center-based",
    "AgeGroup": "Preschool",
    " Median Cost ": "$1,018.00",
    " 75th Percentile\nCost ": "$1,018.00",
    " State Subsidy\nRate ": "$1,018.00",
    "Median Cost\nas a % of Median Income": "20.00%",
    "": ""
  },
  {
    "Year": "2021",
    "County": "Klickitat",
    "Care_Type": "Center-based",
    "AgeGroup": "School Age",
    " Median Cost ": "$433.00",
    " 75th Percentile\nCost ": "$440.00",
    " State Subsidy\nRate ": "$778.00",
    "Median Cost\nas a % of Median Income": "8.00%",
    "": ""
  },
  {
    "Year": "2021",
    "County": "Klickitat",
    "Care_Type": "FCC",
    "AgeGroup": "Infant",
    " Median Cost ": "$1,100.00",
    " 75th Percentile\nCost ": "$1,100.00",
    " State Subsidy\nRate ": "$975.00",
    "Median Cost\nas a % of Median Income": "22.00%",
    "": ""
  },
  {
    "Year": "2021",
    "County": "Klickitat",
    "Care_Type": "FCC",
    "AgeGroup": "Toddler",
    " Median Cost ": "$900.00",
    " 75th Percentile\nCost ": "$900.00",
    " State Subsidy\nRate ": "$936.00",
    "Median Cost\nas a % of Median Income": "18.00%",
    "": ""
  },
  {
    "Year": "2021",
    "County": "Klickitat",
    "Care_Type": "FCC",
    "AgeGroup": "Preschool",
    " Median Cost ": "$900.00",
    " 75th Percentile\nCost ": "$900.00",
    " State Subsidy\nRate ": "$823.00",
    "Median Cost\nas a % of Median Income": "18.00%",
    "": ""
  },
  {
    "Year": "2021",
    "County": "Klickitat",
    "Care_Type": "FCC",
    "AgeGroup": "School Age",
    " Median Cost ": "$600.00",
    " 75th Percentile\nCost ": "$600.00",
    " State Subsidy\nRate ": "$704.00",
    "Median Cost\nas a % of Median Income": "12.00%",
    "": ""
  },
  {
    "Year": "2021",
    "County": "Lewis",
    "Care_Type": "Center-based",
    "AgeGroup": "Infant",
    " Median Cost ": "$1,016.00",
    " 75th Percentile\nCost ": "$1,067.00",
    " State Subsidy\nRate ": "$1,235.00",
    "Median Cost\nas a % of Median Income": "20.00%",
    "": ""
  },
  {
    "Year": "2021",
    "County": "Lewis",
    "Care_Type": "Center-based",
    "AgeGroup": "Toddler",
    " Median Cost ": "$886.00",
    " 75th Percentile\nCost ": "$975.00",
    " State Subsidy\nRate ": "$1,105.00",
    "Median Cost\nas a % of Median Income": "18.00%",
    "": ""
  },
  {
    "Year": "2021",
    "County": "Lewis",
    "Care_Type": "Center-based",
    "AgeGroup": "Preschool",
    " Median Cost ": "$805.00",
    " 75th Percentile\nCost ": "$888.00",
    " State Subsidy\nRate ": "$1,018.00",
    "Median Cost\nas a % of Median Income": "16.00%",
    "": ""
  },
  {
    "Year": "2021",
    "County": "Lewis",
    "Care_Type": "Center-based",
    "AgeGroup": "School Age",
    " Median Cost ": "$585.00",
    " 75th Percentile\nCost ": "$701.00",
    " State Subsidy\nRate ": "$778.00",
    "Median Cost\nas a % of Median Income": "12.00%",
    "": ""
  },
  {
    "Year": "2021",
    "County": "Lewis",
    "Care_Type": "FCC",
    "AgeGroup": "Infant",
    " Median Cost ": "$780.00",
    " 75th Percentile\nCost ": "$850.00",
    " State Subsidy\nRate ": "$975.00",
    "Median Cost\nas a % of Median Income": "16.00%",
    "": ""
  },
  {
    "Year": "2021",
    "County": "Lewis",
    "Care_Type": "FCC",
    "AgeGroup": "Toddler",
    " Median Cost ": "$650.00",
    " 75th Percentile\nCost ": "$688.00",
    " State Subsidy\nRate ": "$936.00",
    "Median Cost\nas a % of Median Income": "13.00%",
    "": ""
  },
  {
    "Year": "2021",
    "County": "Lewis",
    "Care_Type": "FCC",
    "AgeGroup": "Preschool",
    " Median Cost ": "$593.00",
    " 75th Percentile\nCost ": "$637.00",
    " State Subsidy\nRate ": "$823.00",
    "Median Cost\nas a % of Median Income": "12.00%",
    "": ""
  },
  {
    "Year": "2021",
    "County": "Lewis",
    "Care_Type": "FCC",
    "AgeGroup": "School Age",
    " Median Cost ": "$353.00",
    " 75th Percentile\nCost ": "$415.00",
    " State Subsidy\nRate ": "$704.00",
    "Median Cost\nas a % of Median Income": "7.00%",
    "": ""
  },
  {
    "Year": "2021",
    "County": "Lincoln",
    "Care_Type": "Center-based",
    "AgeGroup": "Infant",
    " Median Cost ": "No Rates Ava",
    " 75th Percentile\nCost ": "$0.00",
    " State Subsidy\nRate ": "$897.00",
    "Median Cost\nas a % of Median Income": "NA",
    "": ""
  },
  {
    "Year": "2021",
    "County": "Lincoln",
    "Care_Type": "Center-based",
    "AgeGroup": "Toddler",
    " Median Cost ": "No Rates Ava",
    " 75th Percentile\nCost ": "$0.00",
    " State Subsidy\nRate ": "$813.00",
    "Median Cost\nas a % of Median Income": "NA",
    "": ""
  },
  {
    "Year": "2021",
    "County": "Lincoln",
    "Care_Type": "Center-based",
    "AgeGroup": "Preschool",
    " Median Cost ": "No Rates Ava",
    " 75th Percentile\nCost ": "$0.00",
    " State Subsidy\nRate ": "$741.00",
    "Median Cost\nas a % of Median Income": "NA",
    "": ""
  },
  {
    "Year": "2021",
    "County": "Lincoln",
    "Care_Type": "Center-based",
    "AgeGroup": "School Age",
    " Median Cost ": "No Rates Ava",
    " 75th Percentile\nCost ": "$0.00",
    " State Subsidy\nRate ": "$731.00",
    "Median Cost\nas a % of Median Income": "NA",
    "": ""
  },
  {
    "Year": "2021",
    "County": "Lincoln",
    "Care_Type": "FCC",
    "AgeGroup": "Infant",
    " Median Cost ": "$823.00",
    " 75th Percentile\nCost ": "$823.00",
    " State Subsidy\nRate ": "$867.00",
    "Median Cost\nas a % of Median Income": "17.00%",
    "": ""
  },
  {
    "Year": "2021",
    "County": "Lincoln",
    "Care_Type": "FCC",
    "AgeGroup": "Toddler",
    " Median Cost ": "$823.00",
    " 75th Percentile\nCost ": "$823.00",
    " State Subsidy\nRate ": "$758.00",
    "Median Cost\nas a % of Median Income": "17.00%",
    "": ""
  },
  {
    "Year": "2021",
    "County": "Lincoln",
    "Care_Type": "FCC",
    "AgeGroup": "Preschool",
    " Median Cost ": "$737.00",
    " 75th Percentile\nCost ": "$737.00",
    " State Subsidy\nRate ": "$693.00",
    "Median Cost\nas a % of Median Income": "15.00%",
    "": ""
  },
  {
    "Year": "2021",
    "County": "Lincoln",
    "Care_Type": "FCC",
    "AgeGroup": "School Age",
    " Median Cost ": "$672.00",
    " 75th Percentile\nCost ": "$672.00",
    " State Subsidy\nRate ": "$650.00",
    "Median Cost\nas a % of Median Income": "14.00%",
    "": ""
  },
  {
    "Year": "2021",
    "County": "Mason",
    "Care_Type": "Center-based",
    "AgeGroup": "Infant",
    " Median Cost ": "$1,050.00",
    " 75th Percentile\nCost ": "$1,086.00",
    " State Subsidy\nRate ": "$1,235.00",
    "Median Cost\nas a % of Median Income": "19.00%",
    "": ""
  },
  {
    "Year": "2021",
    "County": "Mason",
    "Care_Type": "Center-based",
    "AgeGroup": "Toddler",
    " Median Cost ": "$958.00",
    " 75th Percentile\nCost ": "$973.00",
    " State Subsidy\nRate ": "$1,105.00",
    "Median Cost\nas a % of Median Income": "17.00%",
    "": ""
  },
  {
    "Year": "2021",
    "County": "Mason",
    "Care_Type": "Center-based",
    "AgeGroup": "Preschool",
    " Median Cost ": "$885.00",
    " 75th Percentile\nCost ": "$914.00",
    " State Subsidy\nRate ": "$1,018.00",
    "Median Cost\nas a % of Median Income": "16.00%",
    "": ""
  },
  {
    "Year": "2021",
    "County": "Mason",
    "Care_Type": "Center-based",
    "AgeGroup": "School Age",
    " Median Cost ": "$704.00",
    " 75th Percentile\nCost ": "$707.00",
    " State Subsidy\nRate ": "$778.00",
    "Median Cost\nas a % of Median Income": "13.00%",
    "": ""
  },
  {
    "Year": "2021",
    "County": "Mason",
    "Care_Type": "FCC",
    "AgeGroup": "Infant",
    " Median Cost ": "$830.00",
    " 75th Percentile\nCost ": "$865.00",
    " State Subsidy\nRate ": "$975.00",
    "Median Cost\nas a % of Median Income": "15.00%",
    "": ""
  },
  {
    "Year": "2021",
    "County": "Mason",
    "Care_Type": "FCC",
    "AgeGroup": "Toddler",
    " Median Cost ": "$750.00",
    " 75th Percentile\nCost ": "$800.00",
    " State Subsidy\nRate ": "$936.00",
    "Median Cost\nas a % of Median Income": "13.00%",
    "": ""
  },
  {
    "Year": "2021",
    "County": "Mason",
    "Care_Type": "FCC",
    "AgeGroup": "Preschool",
    " Median Cost ": "$700.00",
    " 75th Percentile\nCost ": "$738.00",
    " State Subsidy\nRate ": "$823.00",
    "Median Cost\nas a % of Median Income": "12.00%",
    "": ""
  },
  {
    "Year": "2021",
    "County": "Mason",
    "Care_Type": "FCC",
    "AgeGroup": "School Age",
    " Median Cost ": "$563.00",
    " 75th Percentile\nCost ": "$574.00",
    " State Subsidy\nRate ": "$704.00",
    "Median Cost\nas a % of Median Income": "10.00%",
    "": ""
  },
  {
    "Year": "2021",
    "County": "Okanogan",
    "Care_Type": "Center-based",
    "AgeGroup": "Infant",
    " Median Cost ": "$897.00",
    " 75th Percentile\nCost ": "$944.00",
    " State Subsidy\nRate ": "$897.00",
    "Median Cost\nas a % of Median Income": "24.00%",
    "": ""
  },
  {
    "Year": "2021",
    "County": "Okanogan",
    "Care_Type": "Center-based",
    "AgeGroup": "Toddler",
    " Median Cost ": "$813.00",
    " 75th Percentile\nCost ": "$840.00",
    " State Subsidy\nRate ": "$813.00",
    "Median Cost\nas a % of Median Income": "22.00%",
    "": ""
  },
  {
    "Year": "2021",
    "County": "Okanogan",
    "Care_Type": "Center-based",
    "AgeGroup": "Preschool",
    " Median Cost ": "$741.00",
    " 75th Percentile\nCost ": "$769.00",
    " State Subsidy\nRate ": "$741.00",
    "Median Cost\nas a % of Median Income": "20.00%",
    "": ""
  },
  {
    "Year": "2021",
    "County": "Okanogan",
    "Care_Type": "Center-based",
    "AgeGroup": "School Age",
    " Median Cost ": "$650.00",
    " 75th Percentile\nCost ": "$775.00",
    " State Subsidy\nRate ": "$731.00",
    "Median Cost\nas a % of Median Income": "18.00%",
    "": ""
  },
  {
    "Year": "2021",
    "County": "Okanogan",
    "Care_Type": "FCC",
    "AgeGroup": "Infant",
    " Median Cost ": "$975.00",
    " 75th Percentile\nCost ": "$1,083.00",
    " State Subsidy\nRate ": "$867.00",
    "Median Cost\nas a % of Median Income": "27.00%",
    "": ""
  },
  {
    "Year": "2021",
    "County": "Okanogan",
    "Care_Type": "FCC",
    "AgeGroup": "Toddler",
    " Median Cost ": "$888.00",
    " 75th Percentile\nCost ": "$1,083.00",
    " State Subsidy\nRate ": "$758.00",
    "Median Cost\nas a % of Median Income": "24.00%",
    "": ""
  },
  {
    "Year": "2021",
    "County": "Okanogan",
    "Care_Type": "FCC",
    "AgeGroup": "Preschool",
    " Median Cost ": "$758.00",
    " 75th Percentile\nCost ": "$1,029.00",
    " State Subsidy\nRate ": "$693.00",
    "Median Cost\nas a % of Median Income": "21.00%",
    "": ""
  },
  {
    "Year": "2021",
    "County": "Okanogan",
    "Care_Type": "FCC",
    "AgeGroup": "School Age",
    " Median Cost ": "$325.00",
    " 75th Percentile\nCost ": "$567.00",
    " State Subsidy\nRate ": "$650.00",
    "Median Cost\nas a % of Median Income": "9.00%",
    "": ""
  },
  {
    "Year": "2021",
    "County": "Pacific",
    "Care_Type": "Center-based",
    "AgeGroup": "Infant",
    " Median Cost ": "$1,073.00",
    " 75th Percentile\nCost ": "$1,073.00",
    " State Subsidy\nRate ": "$1,235.00",
    "Median Cost\nas a % of Median Income": "26.00%",
    "": ""
  },
  {
    "Year": "2021",
    "County": "Pacific",
    "Care_Type": "Center-based",
    "AgeGroup": "Toddler",
    " Median Cost ": "$932.00",
    " 75th Percentile\nCost ": "$932.00",
    " State Subsidy\nRate ": "$1,105.00",
    "Median Cost\nas a % of Median Income": "23.00%",
    "": ""
  },
  {
    "Year": "2021",
    "County": "Pacific",
    "Care_Type": "Center-based",
    "AgeGroup": "Preschool",
    " Median Cost ": "$542.00",
    " 75th Percentile\nCost ": "$688.00",
    " State Subsidy\nRate ": "$1,018.00",
    "Median Cost\nas a % of Median Income": "13.00%",
    "": ""
  },
  {
    "Year": "2021",
    "County": "Pacific",
    "Care_Type": "Center-based",
    "AgeGroup": "School Age",
    " Median Cost ": "$672.00",
    " 75th Percentile\nCost ": "$672.00",
    " State Subsidy\nRate ": "$778.00",
    "Median Cost\nas a % of Median Income": "16.00%",
    "": ""
  },
  {
    "Year": "2021",
    "County": "Pacific",
    "Care_Type": "FCC",
    "AgeGroup": "Infant",
    " Median Cost ": "$812.00",
    " 75th Percentile\nCost ": "$834.00",
    " State Subsidy\nRate ": "$975.00",
    "Median Cost\nas a % of Median Income": "20.00%",
    "": ""
  },
  {
    "Year": "2021",
    "County": "Pacific",
    "Care_Type": "FCC",
    "AgeGroup": "Toddler",
    " Median Cost ": "$779.00",
    " 75th Percentile\nCost ": "$817.00",
    " State Subsidy\nRate ": "$936.00",
    "Median Cost\nas a % of Median Income": "19.00%",
    "": ""
  },
  {
    "Year": "2021",
    "County": "Pacific",
    "Care_Type": "FCC",
    "AgeGroup": "Preschool",
    " Median Cost ": "$779.00",
    " 75th Percentile\nCost ": "$817.00",
    " State Subsidy\nRate ": "$823.00",
    "Median Cost\nas a % of Median Income": "19.00%",
    "": ""
  },
  {
    "Year": "2021",
    "County": "Pacific",
    "Care_Type": "FCC",
    "AgeGroup": "School Age",
    " Median Cost ": "$704.00",
    " 75th Percentile\nCost ": "$785.00",
    " State Subsidy\nRate ": "$704.00",
    "Median Cost\nas a % of Median Income": "17.00%",
    "": ""
  },
  {
    "Year": "2021",
    "County": "Pend Oreille",
    "Care_Type": "Center-based",
    "AgeGroup": "Infant",
    " Median Cost ": "NA",
    " 75th Percentile\nCost ": "$0.00",
    " State Subsidy\nRate ": "$897.00",
    "Median Cost\nas a % of Median Income": "NA",
    "": ""
  },
  {
    "Year": "2021",
    "County": "Pend Oreille",
    "Care_Type": "Center-based",
    "AgeGroup": "Toddler",
    " Median Cost ": "NA",
    " 75th Percentile\nCost ": "$0.00",
    " State Subsidy\nRate ": "$813.00",
    "Median Cost\nas a % of Median Income": "NA",
    "": ""
  },
  {
    "Year": "2021",
    "County": "Pend Oreille",
    "Care_Type": "Center-based",
    "AgeGroup": "Preschool",
    " Median Cost ": "NA",
    " 75th Percentile\nCost ": "$0.00",
    " State Subsidy\nRate ": "$741.00",
    "Median Cost\nas a % of Median Income": "NA",
    "": ""
  },
  {
    "Year": "2021",
    "County": "Pend Oreille",
    "Care_Type": "Center-based",
    "AgeGroup": "School Age",
    " Median Cost ": "NA",
    " 75th Percentile\nCost ": "$0.00",
    " State Subsidy\nRate ": "$731.00",
    "Median Cost\nas a % of Median Income": "NA",
    "": ""
  },
  {
    "Year": "2021",
    "County": "Pend Oreille",
    "Care_Type": "FCC",
    "AgeGroup": "Infant",
    " Median Cost ": "NA",
    " 75th Percentile\nCost ": "$0.00",
    " State Subsidy\nRate ": "$867.00",
    "Median Cost\nas a % of Median Income": "NA",
    "": ""
  },
  {
    "Year": "2021",
    "County": "Pend Oreille",
    "Care_Type": "FCC",
    "AgeGroup": "Toddler",
    " Median Cost ": "NA",
    " 75th Percentile\nCost ": "$0.00",
    " State Subsidy\nRate ": "$758.00",
    "Median Cost\nas a % of Median Income": "NA",
    "": ""
  },
  {
    "Year": "2021",
    "County": "Pend Oreille",
    "Care_Type": "FCC",
    "AgeGroup": "Preschool",
    " Median Cost ": "NA",
    " 75th Percentile\nCost ": "$0.00",
    " State Subsidy\nRate ": "$693.00",
    "Median Cost\nas a % of Median Income": "NA",
    "": ""
  },
  {
    "Year": "2021",
    "County": "Pend Oreille",
    "Care_Type": "FCC",
    "AgeGroup": "School Age",
    " Median Cost ": "NA",
    " 75th Percentile\nCost ": "$0.00",
    " State Subsidy\nRate ": "$650.00",
    "Median Cost\nas a % of Median Income": "NA",
    "": ""
  },
  {
    "Year": "2021",
    "County": "Pierce",
    "Care_Type": "Center-based",
    "AgeGroup": "Infant",
    " Median Cost ": "$1,300.00",
    " 75th Percentile\nCost ": "$1,484.00",
    " State Subsidy\nRate ": "$1,355.00",
    "Median Cost\nas a % of Median Income": "21.00%",
    "": ""
  },
  {
    "Year": "2021",
    "County": "Pierce",
    "Care_Type": "Center-based",
    "AgeGroup": "Toddler",
    " Median Cost ": "$1,077.00",
    " 75th Percentile\nCost ": "$1,270.00",
    " State Subsidy\nRate ": "$1,173.00",
    "Median Cost\nas a % of Median Income": "17.00%",
    "": ""
  },
  {
    "Year": "2021",
    "County": "Pierce",
    "Care_Type": "Center-based",
    "AgeGroup": "Preschool",
    " Median Cost ": "$953.00",
    " 75th Percentile\nCost ": "$1,111.00",
    " State Subsidy\nRate ": "$1,042.00",
    "Median Cost\nas a % of Median Income": "15.00%",
    "": ""
  },
  {
    "Year": "2021",
    "County": "Pierce",
    "Care_Type": "Center-based",
    "AgeGroup": "School Age",
    " Median Cost ": "$542.00",
    " 75th Percentile\nCost ": "$622.00",
    " State Subsidy\nRate ": "$758.00",
    "Median Cost\nas a % of Median Income": "9.00%",
    "": ""
  },
  {
    "Year": "2021",
    "County": "Pierce",
    "Care_Type": "FCC",
    "AgeGroup": "Infant",
    " Median Cost ": "$975.00",
    " 75th Percentile\nCost ": "$1,171.00",
    " State Subsidy\nRate ": "$1,059.00",
    "Median Cost\nas a % of Median Income": "16.00%",
    "": ""
  },
  {
    "Year": "2021",
    "County": "Pierce",
    "Care_Type": "FCC",
    "AgeGroup": "Toddler",
    " Median Cost ": "$867.00",
    " 75th Percentile\nCost ": "$1,030.00",
    " State Subsidy\nRate ": "$910.00",
    "Median Cost\nas a % of Median Income": "14.00%",
    "": ""
  },
  {
    "Year": "2021",
    "County": "Pierce",
    "Care_Type": "FCC",
    "AgeGroup": "Preschool",
    " Median Cost ": "$823.00",
    " 75th Percentile\nCost ": "$963.00",
    " State Subsidy\nRate ": "$847.00",
    "Median Cost\nas a % of Median Income": "13.00%",
    "": ""
  },
  {
    "Year": "2021",
    "County": "Pierce",
    "Care_Type": "FCC",
    "AgeGroup": "School Age",
    " Median Cost ": "$433.00",
    " 75th Percentile\nCost ": "$650.00",
    " State Subsidy\nRate ": "$774.00",
    "Median Cost\nas a % of Median Income": "7.00%",
    "": ""
  },
  {
    "Year": "2021",
    "County": "San Juan",
    "Care_Type": "Center-based",
    "AgeGroup": "Infant",
    " Median Cost ": "$1,387.00",
    " 75th Percentile\nCost ": "$1,387.00",
    " State Subsidy\nRate ": "$1,654.00",
    "Median Cost\nas a % of Median Income": "23.00%",
    "": ""
  },
  {
    "Year": "2021",
    "County": "San Juan",
    "Care_Type": "Center-based",
    "AgeGroup": "Toddler",
    " Median Cost ": "$1,213.00",
    " 75th Percentile\nCost ": "$1,326.00",
    " State Subsidy\nRate ": "$1,482.00",
    "Median Cost\nas a % of Median Income": "20.00%",
    "": ""
  },
  {
    "Year": "2021",
    "County": "San Juan",
    "Care_Type": "Center-based",
    "AgeGroup": "Preschool",
    " Median Cost ": "$1,040.00",
    " 75th Percentile\nCost ": "$1,209.00",
    " State Subsidy\nRate ": "$1,249.00",
    "Median Cost\nas a % of Median Income": "18.00%",
    "": ""
  },
  {
    "Year": "2021",
    "County": "San Juan",
    "Care_Type": "Center-based",
    "AgeGroup": "School Age",
    " Median Cost ": "$282.00",
    " 75th Percentile\nCost ": "$282.00",
    " State Subsidy\nRate ": "$946.00",
    "Median Cost\nas a % of Median Income": "5.00%",
    "": ""
  },
  {
    "Year": "2021",
    "County": "San Juan",
    "Care_Type": "FCC",
    "AgeGroup": "Infant",
    " Median Cost ": "NA",
    " 75th Percentile\nCost ": "$0.00",
    " State Subsidy\nRate ": "$1,192.00",
    "Median Cost\nas a % of Median Income": "NA",
    "": ""
  },
  {
    "Year": "2021",
    "County": "San Juan",
    "Care_Type": "FCC",
    "AgeGroup": "Toddler",
    " Median Cost ": "NA",
    " 75th Percentile\nCost ": "$0.00",
    " State Subsidy\nRate ": "$1,059.00",
    "Median Cost\nas a % of Median Income": "NA",
    "": ""
  },
  {
    "Year": "2021",
    "County": "San Juan",
    "Care_Type": "FCC",
    "AgeGroup": "Preschool",
    " Median Cost ": "NA",
    " 75th Percentile\nCost ": "$0.00",
    " State Subsidy\nRate ": "$1,040.00",
    "Median Cost\nas a % of Median Income": "NA",
    "": ""
  },
  {
    "Year": "2021",
    "County": "San Juan",
    "Care_Type": "FCC",
    "AgeGroup": "School Age",
    " Median Cost ": "NA",
    " 75th Percentile\nCost ": "$0.00",
    " State Subsidy\nRate ": "$867.00",
    "Median Cost\nas a % of Median Income": "NA",
    "": ""
  },
  {
    "Year": "2021",
    "County": "Skagit",
    "Care_Type": "Center-based",
    "AgeGroup": "Infant",
    " Median Cost ": "$1,363.00",
    " 75th Percentile\nCost ": "$1,474.00",
    " State Subsidy\nRate ": "$1,654.00",
    "Median Cost\nas a % of Median Income": "26.00%",
    "": ""
  },
  {
    "Year": "2021",
    "County": "Skagit",
    "Care_Type": "Center-based",
    "AgeGroup": "Toddler",
    " Median Cost ": "$1,062.00",
    " 75th Percentile\nCost ": "$1,190.00",
    " State Subsidy\nRate ": "$1,482.00",
    "Median Cost\nas a % of Median Income": "21.00%",
    "": ""
  },
  {
    "Year": "2021",
    "County": "Skagit",
    "Care_Type": "Center-based",
    "AgeGroup": "Preschool",
    " Median Cost ": "$888.00",
    " 75th Percentile\nCost ": "$1,057.00",
    " State Subsidy\nRate ": "$1,249.00",
    "Median Cost\nas a % of Median Income": "17.00%",
    "": ""
  },
  {
    "Year": "2021",
    "County": "Skagit",
    "Care_Type": "Center-based",
    "AgeGroup": "School Age",
    " Median Cost ": "$452.00",
    " 75th Percentile\nCost ": "$620.00",
    " State Subsidy\nRate ": "$946.00",
    "Median Cost\nas a % of Median Income": "9.00%",
    "": ""
  },
  {
    "Year": "2021",
    "County": "Skagit",
    "Care_Type": "FCC",
    "AgeGroup": "Infant",
    " Median Cost ": "$997.00",
    " 75th Percentile\nCost ": "$1,150.00",
    " State Subsidy\nRate ": "$1,192.00",
    "Median Cost\nas a % of Median Income": "19.00%",
    "": ""
  },
  {
    "Year": "2021",
    "County": "Skagit",
    "Care_Type": "FCC",
    "AgeGroup": "Toddler",
    " Median Cost ": "$867.00",
    " 75th Percentile\nCost ": "$1,060.00",
    " State Subsidy\nRate ": "$1,059.00",
    "Median Cost\nas a % of Median Income": "17.00%",
    "": ""
  },
  {
    "Year": "2021",
    "County": "Skagit",
    "Care_Type": "FCC",
    "AgeGroup": "Preschool",
    " Median Cost ": "$867.00",
    " 75th Percentile\nCost ": "$1,040.00",
    " State Subsidy\nRate ": "$1,040.00",
    "Median Cost\nas a % of Median Income": "17.00%",
    "": ""
  },
  {
    "Year": "2021",
    "County": "Skagit",
    "Care_Type": "FCC",
    "AgeGroup": "School Age",
    " Median Cost ": "$550.00",
    " 75th Percentile\nCost ": "$650.00",
    " State Subsidy\nRate ": "$867.00",
    "Median Cost\nas a % of Median Income": "11.00%",
    "": ""
  },
  {
    "Year": "2021",
    "County": "Skamania",
    "Care_Type": "Center-based",
    "AgeGroup": "Infant",
    " Median Cost ": "No Rates Ava",
    " 75th Percentile\nCost ": "$0.00",
    " State Subsidy\nRate ": "$1,235.00",
    "Median Cost\nas a % of Median Income": "N/A",
    "": ""
  },
  {
    "Year": "2021",
    "County": "Skamania",
    "Care_Type": "Center-based",
    "AgeGroup": "Toddler",
    " Median Cost ": "No Rates Ava",
    " 75th Percentile\nCost ": "$0.00",
    " State Subsidy\nRate ": "$1,105.00",
    "Median Cost\nas a % of Median Income": "N/A",
    "": ""
  },
  {
    "Year": "2021",
    "County": "Skamania",
    "Care_Type": "Center-based",
    "AgeGroup": "Preschool",
    " Median Cost ": "No Rates Ava",
    " 75th Percentile\nCost ": "$0.00",
    " State Subsidy\nRate ": "$1,018.00",
    "Median Cost\nas a % of Median Income": "N/A",
    "": ""
  },
  {
    "Year": "2021",
    "County": "Skamania",
    "Care_Type": "Center-based",
    "AgeGroup": "School Age",
    " Median Cost ": "No Rates Ava",
    " 75th Percentile\nCost ": "$0.00",
    " State Subsidy\nRate ": "$778.00",
    "Median Cost\nas a % of Median Income": "N/A",
    "": ""
  },
  {
    "Year": "2021",
    "County": "Skamania",
    "Care_Type": "FCC",
    "AgeGroup": "Infant",
    " Median Cost ": "$650.00",
    " 75th Percentile\nCost ": "$704.00",
    " State Subsidy\nRate ": "$975.00",
    "Median Cost\nas a % of Median Income": "12.00%",
    "": ""
  },
  {
    "Year": "2021",
    "County": "Skamania",
    "Care_Type": "FCC",
    "AgeGroup": "Toddler",
    " Median Cost ": "$650.00",
    " 75th Percentile\nCost ": "$704.00",
    " State Subsidy\nRate ": "$936.00",
    "Median Cost\nas a % of Median Income": "12.00%",
    "": ""
  },
  {
    "Year": "2021",
    "County": "Skamania",
    "Care_Type": "FCC",
    "AgeGroup": "Preschool",
    " Median Cost ": "$550.00",
    " 75th Percentile\nCost ": "$600.00",
    " State Subsidy\nRate ": "$823.00",
    "Median Cost\nas a % of Median Income": "10.00%",
    "": ""
  },
  {
    "Year": "2021",
    "County": "Skamania",
    "Care_Type": "FCC",
    "AgeGroup": "School Age",
    " Median Cost ": "$650.00",
    " 75th Percentile\nCost ": "$953.00",
    " State Subsidy\nRate ": "$704.00",
    "Median Cost\nas a % of Median Income": "12.00%",
    "": ""
  },
  {
    "Year": "2021",
    "County": "Snohomish",
    "Care_Type": "Center-based",
    "AgeGroup": "Infant",
    " Median Cost ": "$1,620.00",
    " 75th Percentile\nCost ": "$1,799.00",
    " State Subsidy\nRate ": "$1,654.00",
    "Median Cost\nas a % of Median Income": "22.00%",
    "": ""
  },
  {
    "Year": "2021",
    "County": "Snohomish",
    "Care_Type": "Center-based",
    "AgeGroup": "Toddler",
    " Median Cost ": "$1,365.00",
    " 75th Percentile\nCost ": "$1,604.00",
    " State Subsidy\nRate ": "$1,482.00",
    "Median Cost\nas a % of Median Income": "19.00%",
    "": ""
  },
  {
    "Year": "2021",
    "County": "Snohomish",
    "Care_Type": "Center-based",
    "AgeGroup": "Preschool",
    " Median Cost ": "$1,200.00",
    " 75th Percentile\nCost ": "$1,365.00",
    " State Subsidy\nRate ": "$1,249.00",
    "Median Cost\nas a % of Median Income": "16.00%",
    "": ""
  },
  {
    "Year": "2021",
    "County": "Snohomish",
    "Care_Type": "Center-based",
    "AgeGroup": "School Age",
    " Median Cost ": "$520.00",
    " 75th Percentile\nCost ": "$744.00",
    " State Subsidy\nRate ": "$946.00",
    "Median Cost\nas a % of Median Income": "7.00%",
    "": ""
  },
  {
    "Year": "2021",
    "County": "Snohomish",
    "Care_Type": "FCC",
    "AgeGroup": "Infant",
    " Median Cost ": "$1,192.00",
    " 75th Percentile\nCost ": "$1,387.00",
    " State Subsidy\nRate ": "$1,192.00",
    "Median Cost\nas a % of Median Income": "16.00%",
    "": ""
  },
  {
    "Year": "2021",
    "County": "Snohomish",
    "Care_Type": "FCC",
    "AgeGroup": "Toddler",
    " Median Cost ": "$1,083.00",
    " 75th Percentile\nCost ": "$1,250.00",
    " State Subsidy\nRate ": "$1,059.00",
    "Median Cost\nas a % of Median Income": "15.00%",
    "": ""
  },
  {
    "Year": "2021",
    "County": "Snohomish",
    "Care_Type": "FCC",
    "AgeGroup": "Preschool",
    " Median Cost ": "$975.00",
    " 75th Percentile\nCost ": "$1,192.00",
    " State Subsidy\nRate ": "$1,040.00",
    "Median Cost\nas a % of Median Income": "13.00%",
    "": ""
  },
  {
    "Year": "2021",
    "County": "Snohomish",
    "Care_Type": "FCC",
    "AgeGroup": "School Age",
    " Median Cost ": "$500.00",
    " 75th Percentile\nCost ": "$650.00",
    " State Subsidy\nRate ": "$867.00",
    "Median Cost\nas a % of Median Income": "7.00%",
    "": ""
  },
  {
    "Year": "2021",
    "County": "Spokane",
    "Care_Type": "Center-based",
    "AgeGroup": "Infant",
    " Median Cost ": "$1,175.00",
    " 75th Percentile\nCost ": "$1,300.00",
    " State Subsidy\nRate ": "$1,280.00",
    "Median Cost\nas a % of Median Income": "25.00%",
    "": ""
  },
  {
    "Year": "2021",
    "County": "Spokane",
    "Care_Type": "Center-based",
    "AgeGroup": "Toddler",
    " Median Cost ": "$1,000.00",
    " 75th Percentile\nCost ": "$1,100.00",
    " State Subsidy\nRate ": "$1,034.00",
    "Median Cost\nas a % of Median Income": "21.00%",
    "": ""
  },
  {
    "Year": "2021",
    "County": "Spokane",
    "Care_Type": "Center-based",
    "AgeGroup": "Preschool",
    " Median Cost ": "$900.00",
    " 75th Percentile\nCost ": "$982.00",
    " State Subsidy\nRate ": "$974.00",
    "Median Cost\nas a % of Median Income": "19.00%",
    "": ""
  },
  {
    "Year": "2021",
    "County": "Spokane",
    "Care_Type": "Center-based",
    "AgeGroup": "School Age",
    " Median Cost ": "$585.00",
    " 75th Percentile\nCost ": "$711.00",
    " State Subsidy\nRate ": "$758.00",
    "Median Cost\nas a % of Median Income": "13.00%",
    "": ""
  },
  {
    "Year": "2021",
    "County": "Spokane",
    "Care_Type": "FCC",
    "AgeGroup": "Infant",
    " Median Cost ": "$900.00",
    " 75th Percentile\nCost ": "$976.00",
    " State Subsidy\nRate ": "$910.00",
    "Median Cost\nas a % of Median Income": "19.00%",
    "": ""
  },
  {
    "Year": "2021",
    "County": "Spokane",
    "Care_Type": "FCC",
    "AgeGroup": "Toddler",
    " Median Cost ": "$795.00",
    " 75th Percentile\nCost ": "$952.00",
    " State Subsidy\nRate ": "$867.00",
    "Median Cost\nas a % of Median Income": "17.00%",
    "": ""
  },
  {
    "Year": "2021",
    "County": "Spokane",
    "Care_Type": "FCC",
    "AgeGroup": "Preschool",
    " Median Cost ": "$758.00",
    " 75th Percentile\nCost ": "$867.00",
    " State Subsidy\nRate ": "$802.00",
    "Median Cost\nas a % of Median Income": "16.00%",
    "": ""
  },
  {
    "Year": "2021",
    "County": "Spokane",
    "Care_Type": "FCC",
    "AgeGroup": "School Age",
    " Median Cost ": "$325.00",
    " 75th Percentile\nCost ": "$395.00",
    " State Subsidy\nRate ": "$780.00",
    "Median Cost\nas a % of Median Income": "7.00%",
    "": ""
  },
  {
    "Year": "2021",
    "County": "Stevens",
    "Care_Type": "Center-based",
    "AgeGroup": "Infant",
    " Median Cost ": "$759.00",
    " 75th Percentile\nCost ": "$759.00",
    " State Subsidy\nRate ": "$897.00",
    "Median Cost\nas a % of Median Income": "19.00%",
    "": ""
  },
  {
    "Year": "2021",
    "County": "Stevens",
    "Care_Type": "Center-based",
    "AgeGroup": "Toddler",
    " Median Cost ": "$726.00",
    " 75th Percentile\nCost ": "$769.00",
    " State Subsidy\nRate ": "$813.00",
    "Median Cost\nas a % of Median Income": "18.00%",
    "": ""
  },
  {
    "Year": "2021",
    "County": "Stevens",
    "Care_Type": "Center-based",
    "AgeGroup": "Preschool",
    " Median Cost ": "$636.00",
    " 75th Percentile\nCost ": "$689.00",
    " State Subsidy\nRate ": "$741.00",
    "Median Cost\nas a % of Median Income": "16.00%",
    "": ""
  },
  {
    "Year": "2021",
    "County": "Stevens",
    "Care_Type": "Center-based",
    "AgeGroup": "School Age",
    " Median Cost ": "$883.00",
    " 75th Percentile\nCost ": "$994.00",
    " State Subsidy\nRate ": "$731.00",
    "Median Cost\nas a % of Median Income": "22.00%",
    "": ""
  },
  {
    "Year": "2021",
    "County": "Stevens",
    "Care_Type": "FCC",
    "AgeGroup": "Infant",
    " Median Cost ": "$779.00",
    " 75th Percentile\nCost ": "$800.00",
    " State Subsidy\nRate ": "$867.00",
    "Median Cost\nas a % of Median Income": "20.00%",
    "": ""
  },
  {
    "Year": "2021",
    "County": "Stevens",
    "Care_Type": "FCC",
    "AgeGroup": "Toddler",
    " Median Cost ": "$628.00",
    " 75th Percentile\nCost ": "$769.00",
    " State Subsidy\nRate ": "$758.00",
    "Median Cost\nas a % of Median Income": "16.00%",
    "": ""
  },
  {
    "Year": "2021",
    "County": "Stevens",
    "Care_Type": "FCC",
    "AgeGroup": "Preschool",
    " Median Cost ": "$683.00",
    " 75th Percentile\nCost ": "$758.00",
    " State Subsidy\nRate ": "$693.00",
    "Median Cost\nas a % of Median Income": "17.00%",
    "": ""
  },
  {
    "Year": "2021",
    "County": "Stevens",
    "Care_Type": "FCC",
    "AgeGroup": "School Age",
    " Median Cost ": "$390.00",
    " 75th Percentile\nCost ": "$444.00",
    " State Subsidy\nRate ": "$650.00",
    "Median Cost\nas a % of Median Income": "10.00%",
    "": ""
  },
  {
    "Year": "2021",
    "County": "Thurston",
    "Care_Type": "Center-based",
    "AgeGroup": "Infant",
    " Median Cost ": "$1,283.00",
    " 75th Percentile\nCost ": "$1,493.00",
    " State Subsidy\nRate ": "$1,235.00",
    "Median Cost\nas a % of Median Income": "21.00%",
    "": ""
  },
  {
    "Year": "2021",
    "County": "Thurston",
    "Care_Type": "Center-based",
    "AgeGroup": "Toddler",
    " Median Cost ": "$1,133.00",
    " 75th Percentile\nCost ": "$1,240.00",
    " State Subsidy\nRate ": "$1,105.00",
    "Median Cost\nas a % of Median Income": "18.00%",
    "": ""
  },
  {
    "Year": "2021",
    "County": "Thurston",
    "Care_Type": "Center-based",
    "AgeGroup": "Preschool",
    " Median Cost ": "$1,039.00",
    " 75th Percentile\nCost ": "$1,148.00",
    " State Subsidy\nRate ": "$1,018.00",
    "Median Cost\nas a % of Median Income": "17.00%",
    "": ""
  },
  {
    "Year": "2021",
    "County": "Thurston",
    "Care_Type": "Center-based",
    "AgeGroup": "School Age",
    " Median Cost ": "$600.00",
    " 75th Percentile\nCost ": "$691.00",
    " State Subsidy\nRate ": "$778.00",
    "Median Cost\nas a % of Median Income": "10.00%",
    "": ""
  },
  {
    "Year": "2021",
    "County": "Thurston",
    "Care_Type": "FCC",
    "AgeGroup": "Infant",
    " Median Cost ": "$975.00",
    " 75th Percentile\nCost ": "$1,113.00",
    " State Subsidy\nRate ": "$975.00",
    "Median Cost\nas a % of Median Income": "16.00%",
    "": ""
  },
  {
    "Year": "2021",
    "County": "Thurston",
    "Care_Type": "FCC",
    "AgeGroup": "Toddler",
    " Median Cost ": "$900.00",
    " 75th Percentile\nCost ": "$970.00",
    " State Subsidy\nRate ": "$936.00",
    "Median Cost\nas a % of Median Income": "14.00%",
    "": ""
  },
  {
    "Year": "2021",
    "County": "Thurston",
    "Care_Type": "FCC",
    "AgeGroup": "Preschool",
    " Median Cost ": "$788.00",
    " 75th Percentile\nCost ": "$873.00",
    " State Subsidy\nRate ": "$823.00",
    "Median Cost\nas a % of Median Income": "13.00%",
    "": ""
  },
  {
    "Year": "2021",
    "County": "Thurston",
    "Care_Type": "FCC",
    "AgeGroup": "School Age",
    " Median Cost ": "$477.00",
    " 75th Percentile\nCost ": "$574.00",
    " State Subsidy\nRate ": "$704.00",
    "Median Cost\nas a % of Median Income": "8.00%",
    "": ""
  },
  {
    "Year": "2021",
    "County": "Wahkiakum",
    "Care_Type": "Center-based",
    "AgeGroup": "Infant",
    " Median Cost ": "NA",
    " 75th Percentile\nCost ": "NA",
    " State Subsidy\nRate ": "$1,235.00",
    "Median Cost\nas a % of Median Income": "NA",
    "": ""
  },
  {
    "Year": "2021",
    "County": "Wahkiakum",
    "Care_Type": "Center-based",
    "AgeGroup": "Toddler",
    " Median Cost ": "NA",
    " 75th Percentile\nCost ": "NA",
    " State Subsidy\nRate ": "$1,105.00",
    "Median Cost\nas a % of Median Income": "NA",
    "": ""
  },
  {
    "Year": "2021",
    "County": "Wahkiakum",
    "Care_Type": "Center-based",
    "AgeGroup": "Preschool",
    " Median Cost ": "NA",
    " 75th Percentile\nCost ": "NA",
    " State Subsidy\nRate ": "$1,018.00",
    "Median Cost\nas a % of Median Income": "NA",
    "": ""
  },
  {
    "Year": "2021",
    "County": "Wahkiakum",
    "Care_Type": "Center-based",
    "AgeGroup": "School Age",
    " Median Cost ": "NA",
    " 75th Percentile\nCost ": "NA",
    " State Subsidy\nRate ": "$778.00",
    "Median Cost\nas a % of Median Income": "NA",
    "": ""
  },
  {
    "Year": "2021",
    "County": "Wahkiakum",
    "Care_Type": "FCC",
    "AgeGroup": "Infant",
    " Median Cost ": "NA",
    " 75th Percentile\nCost ": "NA",
    " State Subsidy\nRate ": "$975.00",
    "Median Cost\nas a % of Median Income": "NA",
    "": ""
  },
  {
    "Year": "2021",
    "County": "Wahkiakum",
    "Care_Type": "FCC",
    "AgeGroup": "Toddler",
    " Median Cost ": "NA",
    " 75th Percentile\nCost ": "NA",
    " State Subsidy\nRate ": "$936.00",
    "Median Cost\nas a % of Median Income": "NA",
    "": ""
  },
  {
    "Year": "2021",
    "County": "Wahkiakum",
    "Care_Type": "FCC",
    "AgeGroup": "Preschool",
    " Median Cost ": "NA",
    " 75th Percentile\nCost ": "NA",
    " State Subsidy\nRate ": "$823.00",
    "Median Cost\nas a % of Median Income": "NA",
    "": ""
  },
  {
    "Year": "2021",
    "County": "Wahkiakum",
    "Care_Type": "FCC",
    "AgeGroup": "School Age",
    " Median Cost ": "NA",
    " 75th Percentile\nCost ": "NA",
    " State Subsidy\nRate ": "$704.00",
    "Median Cost\nas a % of Median Income": "NA",
    "": ""
  },
  {
    "Year": "2021",
    "County": "Walla Walla",
    "Care_Type": "Center-based",
    "AgeGroup": "Infant",
    " Median Cost ": "$1,135.00",
    " 75th Percentile\nCost ": "$1,249.00",
    " State Subsidy\nRate ": "$1,235.00",
    "Median Cost\nas a % of Median Income": "23.00%",
    "": ""
  },
  {
    "Year": "2021",
    "County": "Walla Walla",
    "Care_Type": "Center-based",
    "AgeGroup": "Toddler",
    " Median Cost ": "$1,107.00",
    " 75th Percentile\nCost ": "$1,203.00",
    " State Subsidy\nRate ": "$1,105.00",
    "Median Cost\nas a % of Median Income": "23.00%",
    "": ""
  },
  {
    "Year": "2021",
    "County": "Walla Walla",
    "Care_Type": "Center-based",
    "AgeGroup": "Preschool",
    " Median Cost ": "$867.00",
    " 75th Percentile\nCost ": "$1,067.00",
    " State Subsidy\nRate ": "$1,018.00",
    "Median Cost\nas a % of Median Income": "18.00%",
    "": ""
  },
  {
    "Year": "2021",
    "County": "Walla Walla",
    "Care_Type": "Center-based",
    "AgeGroup": "School Age",
    " Median Cost ": "$722.00",
    " 75th Percentile\nCost ": "$736.00",
    " State Subsidy\nRate ": "$778.00",
    "Median Cost\nas a % of Median Income": "15.00%",
    "": ""
  },
  {
    "Year": "2021",
    "County": "Walla Walla",
    "Care_Type": "FCC",
    "AgeGroup": "Infant",
    " Median Cost ": "$898.00",
    " 75th Percentile\nCost ": "$1,300.00",
    " State Subsidy\nRate ": "$975.00",
    "Median Cost\nas a % of Median Income": "18.00%",
    "": ""
  },
  {
    "Year": "2021",
    "County": "Walla Walla",
    "Care_Type": "FCC",
    "AgeGroup": "Toddler",
    " Median Cost ": "$845.00",
    " 75th Percentile\nCost ": "$1,262.00",
    " State Subsidy\nRate ": "$813.00",
    "Median Cost\nas a % of Median Income": "17.00%",
    "": ""
  },
  {
    "Year": "2021",
    "County": "Walla Walla",
    "Care_Type": "FCC",
    "AgeGroup": "Preschool",
    " Median Cost ": "$758.00",
    " 75th Percentile\nCost ": "$867.00",
    " State Subsidy\nRate ": "$758.00",
    "Median Cost\nas a % of Median Income": "16.00%",
    "": ""
  },
  {
    "Year": "2021",
    "County": "Walla Walla",
    "Care_Type": "FCC",
    "AgeGroup": "School Age",
    " Median Cost ": "$314.00",
    " 75th Percentile\nCost ": "$402.00",
    " State Subsidy\nRate ": "$693.00",
    "Median Cost\nas a % of Median Income": "6.00%",
    "": ""
  },
  {
    "Year": "2021",
    "County": "Whatcom",
    "Care_Type": "Center-based",
    "AgeGroup": "Infant",
    " Median Cost ": "$1,460.00",
    " 75th Percentile\nCost ": "$1,668.00",
    " State Subsidy\nRate ": "$1,654.00",
    "Median Cost\nas a % of Median Income": "26.00%",
    "": ""
  },
  {
    "Year": "2021",
    "County": "Whatcom",
    "Care_Type": "Center-based",
    "AgeGroup": "Toddler",
    " Median Cost ": "$1,413.00",
    " 75th Percentile\nCost ": "$1,517.00",
    " State Subsidy\nRate ": "$1,482.00",
    "Median Cost\nas a % of Median Income": "25.00%",
    "": ""
  },
  {
    "Year": "2021",
    "County": "Whatcom",
    "Care_Type": "Center-based",
    "AgeGroup": "Preschool",
    " Median Cost ": "$1,181.00",
    " 75th Percentile\nCost ": "$1,300.00",
    " State Subsidy\nRate ": "$1,249.00",
    "Median Cost\nas a % of Median Income": "21.00%",
    "": ""
  },
  {
    "Year": "2021",
    "County": "Whatcom",
    "Care_Type": "Center-based",
    "AgeGroup": "School Age",
    " Median Cost ": "$628.00",
    " 75th Percentile\nCost ": "$689.00",
    " State Subsidy\nRate ": "$946.00",
    "Median Cost\nas a % of Median Income": "11.00%",
    "": ""
  },
  {
    "Year": "2021",
    "County": "Whatcom",
    "Care_Type": "FCC",
    "AgeGroup": "Infant",
    " Median Cost ": "$1,083.00",
    " 75th Percentile\nCost ": "$1,210.00",
    " State Subsidy\nRate ": "$1,192.00",
    "Median Cost\nas a % of Median Income": "19.00%",
    "": ""
  },
  {
    "Year": "2021",
    "County": "Whatcom",
    "Care_Type": "FCC",
    "AgeGroup": "Toddler",
    " Median Cost ": "$1,011.00",
    " 75th Percentile\nCost ": "$1,083.00",
    " State Subsidy\nRate ": "$1,059.00",
    "Median Cost\nas a % of Median Income": "18.00%",
    "": ""
  },
  {
    "Year": "2021",
    "County": "Whatcom",
    "Care_Type": "FCC",
    "AgeGroup": "Preschool",
    " Median Cost ": "$939.00",
    " 75th Percentile\nCost ": "$1,051.00",
    " State Subsidy\nRate ": "$1,040.00",
    "Median Cost\nas a % of Median Income": "17.00%",
    "": ""
  },
  {
    "Year": "2021",
    "County": "Whatcom",
    "Care_Type": "FCC",
    "AgeGroup": "School Age",
    " Median Cost ": "$542.00",
    " 75th Percentile\nCost ": "$618.00",
    " State Subsidy\nRate ": "$867.00",
    "Median Cost\nas a % of Median Income": "10.00%",
    "": ""
  },
  {
    "Year": "2021",
    "County": "Whitman",
    "Care_Type": "Center-based",
    "AgeGroup": "Infant",
    " Median Cost ": "$1,402.00",
    " 75th Percentile\nCost ": "$1,543.00",
    " State Subsidy\nRate ": "$1,235.00",
    "Median Cost\nas a % of Median Income": "31.00%",
    "": ""
  },
  {
    "Year": "2021",
    "County": "Whitman",
    "Care_Type": "Center-based",
    "AgeGroup": "Toddler",
    " Median Cost ": "$1,218.00",
    " 75th Percentile\nCost ": "$1,394.00",
    " State Subsidy\nRate ": "$1,105.00",
    "Median Cost\nas a % of Median Income": "27.00%",
    "": ""
  },
  {
    "Year": "2021",
    "County": "Whitman",
    "Care_Type": "Center-based",
    "AgeGroup": "Preschool",
    " Median Cost ": "$1,055.00",
    " 75th Percentile\nCost ": "$1,205.00",
    " State Subsidy\nRate ": "$1,018.00",
    "Median Cost\nas a % of Median Income": "24.00%",
    "": ""
  },
  {
    "Year": "2021",
    "County": "Whitman",
    "Care_Type": "Center-based",
    "AgeGroup": "School Age",
    " Median Cost ": "$464.00",
    " 75th Percentile\nCost ": "$583.00",
    " State Subsidy\nRate ": "$778.00",
    "Median Cost\nas a % of Median Income": "10.00%",
    "": ""
  },
  {
    "Year": "2021",
    "County": "Whitman",
    "Care_Type": "FCC",
    "AgeGroup": "Infant",
    " Median Cost ": "NA",
    " 75th Percentile\nCost ": "NA",
    " State Subsidy\nRate ": "$867.00",
    "Median Cost\nas a % of Median Income": "NA",
    "": ""
  },
  {
    "Year": "2021",
    "County": "Whitman",
    "Care_Type": "FCC",
    "AgeGroup": "Toddler",
    " Median Cost ": "NA",
    " 75th Percentile\nCost ": "NA",
    " State Subsidy\nRate ": "$758.00",
    "Median Cost\nas a % of Median Income": "NA",
    "": ""
  },
  {
    "Year": "2021",
    "County": "Whitman",
    "Care_Type": "FCC",
    "AgeGroup": "Preschool",
    " Median Cost ": "NA",
    " 75th Percentile\nCost ": "NA",
    " State Subsidy\nRate ": "$693.00",
    "Median Cost\nas a % of Median Income": "NA",
    "": ""
  },
  {
    "Year": "2021",
    "County": "Whitman",
    "Care_Type": "FCC",
    "AgeGroup": "School Age",
    " Median Cost ": "NA",
    " 75th Percentile\nCost ": "NA",
    " State Subsidy\nRate ": "$650.00",
    "Median Cost\nas a % of Median Income": "NA",
    "": ""
  },
  {
    "Year": "2021",
    "County": "Yakima",
    "Care_Type": "Center-based",
    "AgeGroup": "Infant",
    " Median Cost ": "$1,078.00",
    " 75th Percentile\nCost ": "$1,192.00",
    " State Subsidy\nRate ": "$1,040.00",
    "Median Cost\nas a % of Median Income": "24.00%",
    "": ""
  },
  {
    "Year": "2021",
    "County": "Yakima",
    "Care_Type": "Center-based",
    "AgeGroup": "Toddler",
    " Median Cost ": "$823.00",
    " 75th Percentile\nCost ": "$939.00",
    " State Subsidy\nRate ": "$793.00",
    "Median Cost\nas a % of Median Income": "18.00%",
    "": ""
  },
  {
    "Year": "2021",
    "County": "Yakima",
    "Care_Type": "Center-based",
    "AgeGroup": "Preschool",
    " Median Cost ": "$791.00",
    " 75th Percentile\nCost ": "$867.00",
    " State Subsidy\nRate ": "$791.00",
    "Median Cost\nas a % of Median Income": "18.00%",
    "": ""
  },
  {
    "Year": "2021",
    "County": "Yakima",
    "Care_Type": "Center-based",
    "AgeGroup": "School Age",
    " Median Cost ": "$593.00",
    " 75th Percentile\nCost ": "$646.00",
    " State Subsidy\nRate ": "$593.00",
    "Median Cost\nas a % of Median Income": "13.00%",
    "": ""
  },
  {
    "Year": "2021",
    "County": "Yakima",
    "Care_Type": "FCC",
    "AgeGroup": "Infant",
    " Median Cost ": "$975.00",
    " 75th Percentile\nCost ": "$1,083.00",
    " State Subsidy\nRate ": "$975.00",
    "Median Cost\nas a % of Median Income": "22.00%",
    "": ""
  },
  {
    "Year": "2021",
    "County": "Yakima",
    "Care_Type": "FCC",
    "AgeGroup": "Toddler",
    " Median Cost ": "$813.00",
    " 75th Percentile\nCost ": "$975.00",
    " State Subsidy\nRate ": "$813.00",
    "Median Cost\nas a % of Median Income": "18.00%",
    "": ""
  },
  {
    "Year": "2021",
    "County": "Yakima",
    "Care_Type": "FCC",
    "AgeGroup": "Preschool",
    " Median Cost ": "$758.00",
    " 75th Percentile\nCost ": "$867.00",
    " State Subsidy\nRate ": "$758.00",
    "Median Cost\nas a % of Median Income": "17.00%",
    "": ""
  },
  {
    "Year": "2021",
    "County": "Yakima",
    "Care_Type": "FCC",
    "AgeGroup": "School Age",
    " Median Cost ": "$303.00",
    " 75th Percentile\nCost ": "$433.00",
    " State Subsidy\nRate ": "$693.00",
    "Median Cost\nas a % of Median Income": "7.00%",
    "": ""
  },
  {
    "Year": "2021",
    "County": "Jefferson",
    "Care_Type": "Center-based",
    "AgeGroup": "Infant",
    " Median Cost ": "NA",
    " 75th Percentile\nCost ": "NA",
    " State Subsidy\nRate ": "$1,235.00",
    "Median Cost\nas a % of Median Income": "NA",
    "": ""
  },
  {
    "Year": "2021",
    "County": "Jefferson",
    "Care_Type": "Center-based",
    "AgeGroup": "Toddler",
    " Median Cost ": "NA",
    " 75th Percentile\nCost ": "NA",
    " State Subsidy\nRate ": "$1,105.00",
    "Median Cost\nas a % of Median Income": "NA",
    "": ""
  },
  {
    "Year": "2021",
    "County": "Jefferson",
    "Care_Type": "Center-based",
    "AgeGroup": "Preschool",
    " Median Cost ": "NA",
    " 75th Percentile\nCost ": "NA",
    " State Subsidy\nRate ": "$1,018.00",
    "Median Cost\nas a % of Median Income": "NA",
    "": ""
  },
  {
    "Year": "2021",
    "County": "Jefferson",
    "Care_Type": "Center-based",
    "AgeGroup": "School Age",
    " Median Cost ": "NA",
    " 75th Percentile\nCost ": "NA",
    " State Subsidy\nRate ": "$778.00",
    "Median Cost\nas a % of Median Income": "NA",
    "": ""
  },
  {
    "Year": "2021",
    "County": "Jefferson",
    "Care_Type": "FCC",
    "AgeGroup": "Infant",
    " Median Cost ": "$1,094.00",
    " 75th Percentile\nCost ": "$1,143.00",
    " State Subsidy\nRate ": "$975.00",
    "Median Cost\nas a % of Median Income": "21.00%",
    "": ""
  },
  {
    "Year": "2021",
    "County": "Jefferson",
    "Care_Type": "FCC",
    "AgeGroup": "Toddler",
    " Median Cost ": "$997.00",
    " 75th Percentile\nCost ": "$1,094.00",
    " State Subsidy\nRate ": "$936.00",
    "Median Cost\nas a % of Median Income": "19.00%",
    "": ""
  },
  {
    "Year": "2021",
    "County": "Jefferson",
    "Care_Type": "FCC",
    "AgeGroup": "Preschool",
    " Median Cost ": "$997.00",
    " 75th Percentile\nCost ": "$1,094.00",
    " State Subsidy\nRate ": "$823.00",
    "Median Cost\nas a % of Median Income": "19.00%",
    "": ""
  },
  {
    "Year": "2021",
    "County": "Jefferson",
    "Care_Type": "FCC",
    "AgeGroup": "School Age",
    " Median Cost ": "$539.00",
    " 75th Percentile\nCost ": "$659.00",
    " State Subsidy\nRate ": "$704.00",
    "Median Cost\nas a % of Median Income": "10.00%",
    "": ""
  }
]
